{
"instructions_readme": "1) Open Chrome, 2) go to chrome://tracing, 3) click Load, 4) navigate to this file.",

"traceEvents":[
{ "pid": 1, "tid": 1, "ph": "M", "name": "thread_name", "args": { "name": "" } },
{ "pid": 1, "tid": 1, "ts": 5.29999984428287, "dur": 132478234.375, "ph": "X", "name": "il2cpp.exe", "args": { "durationMS": 132478.234375, "detail": "" } },
{ "pid": 1, "tid": 1, "ts": 801127.685546875, "dur": 39949972.65625, "ph": "X", "name": "ConvertAssemblies", "args": { "durationMS": 39949.97265625, "detail": "" } },
{ "pid": 1, "tid": 1, "ts": 872223.510742188, "dur": 178860.397338867, "ph": "X", "name": "Collect assemblies to convert", "args": { "durationMS": 178.860397338867, "detail": "" } },
{ "pid": 1, "tid": 1, "ts": 1051338.01269531, "dur": 97447.3037719727, "ph": "X", "name": "RegisterCorlib", "args": { "durationMS": 97.4473037719727, "detail": "" } },
{ "pid": 1, "tid": 1, "ts": 1149213.74511719, "dur": 124135.299682617, "ph": "X", "name": "PreProcessIL", "args": { "durationMS": 124.135299682617, "detail": "" } },
{ "pid": 1, "tid": 1, "ts": 1149214.72167969, "dur": 19597.9995727539, "ph": "X", "name": "Inject base types and finalizers into COM and Windows Runtime types", "args": { "durationMS": 19.5979995727539, "detail": "" } },
{ "pid": 1, "tid": 1, "ts": 1149638.42773438, "dur": 13597.1012115479, "ph": "X", "name": "ModifyCOMAndWindowsRuntimeTypes in assembly", "args": { "durationMS": 13.5971012115479, "detail": "mscorlib" } },
{ "pid": 1, "tid": 1, "ts": 1163237.3046875, "dur": 1955.10005950928, "ph": "X", "name": "ModifyCOMAndWindowsRuntimeTypes in assembly", "args": { "durationMS": 1.95510005950928, "detail": "System.Xml" } },
{ "pid": 1, "tid": 1, "ts": 1166463.74511719, "dur": 1166.100025177, "ph": "X", "name": "ModifyCOMAndWindowsRuntimeTypes in assembly", "args": { "durationMS": 1.166100025177, "detail": "UnityEngine.CoreModule" } },
{ "pid": 1, "tid": 1, "ts": 1167901.48925781, "dur": 677.39999294281, "ph": "X", "name": "ModifyCOMAndWindowsRuntimeTypes in assembly", "args": { "durationMS": 0.67739999294281, "detail": "UnityEngine.UI" } },
{ "pid": 1, "tid": 1, "ts": 1168812.86621094, "dur": 104534.599304199, "ph": "X", "name": "ApplyDefaultMarshalAsAttribute", "args": { "durationMS": 104.534599304199, "detail": "" } },
{ "pid": 1, "tid": 1, "ts": 1169173.95019531, "dur": 71269.5999145508, "ph": "X", "name": "ApplyDefaultMarshalAsAttributeVisitor in assembly", "args": { "durationMS": 71.2695999145508, "detail": "mscorlib" } },
{ "pid": 1, "tid": 1, "ts": 1240462.28027344, "dur": 4830.80005645752, "ph": "X", "name": "ApplyDefaultMarshalAsAttributeVisitor in assembly", "args": { "durationMS": 4.83080005645752, "detail": "System" } },
{ "pid": 1, "tid": 1, "ts": 1245612.42675781, "dur": 2676.89990997314, "ph": "X", "name": "ApplyDefaultMarshalAsAttributeVisitor in assembly", "args": { "durationMS": 2.67689990997314, "detail": "UnityEngine.CoreModule" } },
{ "pid": 1, "tid": 1, "ts": 1248813.59863281, "dur": 377.20000743866, "ph": "X", "name": "ApplyDefaultMarshalAsAttributeVisitor in assembly", "args": { "durationMS": 0.37720000743866, "detail": "UnityEngine.IMGUIModule" } },
{ "pid": 1, "tid": 1, "ts": 1249981.4453125, "dur": 1256.39998912811, "ph": "X", "name": "ApplyDefaultMarshalAsAttributeVisitor in assembly", "args": { "durationMS": 1.25639998912811, "detail": "Unity.Timeline" } },
{ "pid": 1, "tid": 1, "ts": 1251238.76953125, "dur": 2151.20005607605, "ph": "X", "name": "ApplyDefaultMarshalAsAttributeVisitor in assembly", "args": { "durationMS": 2.15120005607605, "detail": "UnityEngine.UI" } },
{ "pid": 1, "tid": 1, "ts": 1253451.171875, "dur": 19774.3015289307, "ph": "X", "name": "ApplyDefaultMarshalAsAttributeVisitor in assembly", "args": { "durationMS": 19.7743015289307, "detail": "Cinemachine" } },
{ "pid": 1, "tid": 1, "ts": 1273692.74902344, "dur": 15779.9005508423, "ph": "X", "name": "WriteResources", "args": { "durationMS": 15.7799005508423, "detail": "" } },
{ "pid": 1, "tid": 1, "ts": 1289947.265625, "dur": 1272445.92285156, "ph": "X", "name": "CopyEtcFolder", "args": { "durationMS": 1272.44592285156, "detail": "" } },
{ "pid": 1, "tid": 1, "ts": 2563135.25390625, "dur": 511237.365722656, "ph": "X", "name": "PreProcessStage", "args": { "durationMS": 511.237365722656, "detail": "" } },
{ "pid": 1, "tid": 1, "ts": 3074382.08007813, "dur": 5102.79989242554, "ph": "X", "name": "Debugger Sequence Points", "args": { "durationMS": 5.10279989242554, "detail": "" } },
{ "pid": 1, "tid": 1, "ts": 3080977.78320313, "dur": 2328663.57421875, "ph": "X", "name": "Generics Collection", "args": { "durationMS": 2328.66357421875, "detail": "" } },
{ "pid": 1, "tid": 1, "ts": 3080978.515625, "dur": 2317975.5859375, "ph": "X", "name": "GenericsCollector.Collect", "args": { "durationMS": 2317.9755859375, "detail": "" } },
{ "pid": 1, "tid": 1, "ts": 5398954.58984375, "dur": 8568.40038299561, "ph": "X", "name": "CollectGenericVirtualMethods.Collect", "args": { "durationMS": 8.56840038299561, "detail": "" } },
{ "pid": 1, "tid": 1, "ts": 5407523.4375, "dur": 1744.30000782013, "ph": "X", "name": "AddExtraTypes", "args": { "durationMS": 1.74430000782013, "detail": "" } },
{ "pid": 1, "tid": 1, "ts": 5409641.6015625, "dur": 2550.19998550415, "ph": "X", "name": "Add Windows Runtime type names", "args": { "durationMS": 2.55019998550415, "detail": "" } },
{ "pid": 1, "tid": 1, "ts": 5409641.6015625, "dur": 2549.49998855591, "ph": "X", "name": "Add Windows Runtime type names", "args": { "durationMS": 2.54949998855591, "detail": "" } },
{ "pid": 1, "tid": 1, "ts": 5422890.13671875, "dur": 13428458.984375, "ph": "X", "name": "AllAssemblyConversion", "args": { "durationMS": 13428.458984375, "detail": "" } },
{ "pid": 1, "tid": 1, "ts": 5430098.6328125, "dur": 6587083.984375, "ph": "X", "name": "Convert", "args": { "durationMS": 6587.083984375, "detail": "mscorlib" } },
{ "pid": 1, "tid": 1, "ts": 5430103.02734375, "dur": 6587078.61328125, "ph": "X", "name": "Code", "args": { "durationMS": 6587.07861328125, "detail": "" } },
{ "pid": 1, "tid": 1, "ts": 5430982.421875, "dur": 6586198.73046875, "ph": "X", "name": "Methods", "args": { "durationMS": 6586.19873046875, "detail": "Definitions" } },
{ "pid": 1, "tid": 1, "ts": 12028290.0390625, "dur": 4044.70014572144, "ph": "X", "name": "Convert", "args": { "durationMS": 4.04470014572144, "detail": "System.Xml" } },
{ "pid": 1, "tid": 1, "ts": 12028294.921875, "dur": 4039.8998260498, "ph": "X", "name": "Code", "args": { "durationMS": 4.0398998260498, "detail": "" } },
{ "pid": 1, "tid": 1, "ts": 12028314.453125, "dur": 4019.10018920898, "ph": "X", "name": "Methods", "args": { "durationMS": 4.01910018920898, "detail": "Definitions" } },
{ "pid": 1, "tid": 1, "ts": 12039643.5546875, "dur": 711842.712402344, "ph": "X", "name": "Convert", "args": { "durationMS": 711.842712402344, "detail": "System" } },
{ "pid": 1, "tid": 1, "ts": 12039652.34375, "dur": 711834.228515625, "ph": "X", "name": "Code", "args": { "durationMS": 711.834228515625, "detail": "" } },
{ "pid": 1, "tid": 1, "ts": 12039739.2578125, "dur": 711746.215820313, "ph": "X", "name": "Methods", "args": { "durationMS": 711.746215820313, "detail": "Definitions" } },
{ "pid": 1, "tid": 1, "ts": 12762780.2734375, "dur": 40628.0975341797, "ph": "X", "name": "Convert", "args": { "durationMS": 40.6280975341797, "detail": "System.Configuration" } },
{ "pid": 1, "tid": 1, "ts": 12762787.109375, "dur": 40620.8000183105, "ph": "X", "name": "Code", "args": { "durationMS": 40.6208000183105, "detail": "" } },
{ "pid": 1, "tid": 1, "ts": 12762806.640625, "dur": 40600.2998352051, "ph": "X", "name": "Methods", "args": { "durationMS": 40.6002998352051, "detail": "Definitions" } },
{ "pid": 1, "tid": 1, "ts": 12814084.9609375, "dur": 40102.7984619141, "ph": "X", "name": "Convert", "args": { "durationMS": 40.1027984619141, "detail": "Mono.Security" } },
{ "pid": 1, "tid": 1, "ts": 12814089.84375, "dur": 40097.0001220703, "ph": "X", "name": "Code", "args": { "durationMS": 40.0970001220703, "detail": "" } },
{ "pid": 1, "tid": 1, "ts": 12814102.5390625, "dur": 40083.6982727051, "ph": "X", "name": "Methods", "args": { "durationMS": 40.0836982727051, "detail": "Definitions" } },
{ "pid": 1, "tid": 1, "ts": 12866051.7578125, "dur": 19363.1000518799, "ph": "X", "name": "Convert", "args": { "durationMS": 19.3631000518799, "detail": "System.Core" } },
{ "pid": 1, "tid": 1, "ts": 12866056.640625, "dur": 19357.7995300293, "ph": "X", "name": "Code", "args": { "durationMS": 19.3577995300293, "detail": "" } },
{ "pid": 1, "tid": 1, "ts": 12866072.265625, "dur": 19341.1998748779, "ph": "X", "name": "Methods", "args": { "durationMS": 19.3411998748779, "detail": "Definitions" } },
{ "pid": 1, "tid": 1, "ts": 12894885.7421875, "dur": 66587.3031616211, "ph": "X", "name": "Convert", "args": { "durationMS": 66.5873031616211, "detail": "UnityEngine.SharedInternalsModule" } },
{ "pid": 1, "tid": 1, "ts": 12894891.6015625, "dur": 66580.4977416992, "ph": "X", "name": "Code", "args": { "durationMS": 66.5804977416992, "detail": "" } },
{ "pid": 1, "tid": 1, "ts": 12894913.0859375, "dur": 66558.2046508789, "ph": "X", "name": "Methods", "args": { "durationMS": 66.5582046508789, "detail": "Definitions" } },
{ "pid": 1, "tid": 1, "ts": 12971675.78125, "dur": 871083.129882813, "ph": "X", "name": "Convert", "args": { "durationMS": 871.083129882813, "detail": "UnityEngine.CoreModule" } },
{ "pid": 1, "tid": 1, "ts": 12971680.6640625, "dur": 871078.308105469, "ph": "X", "name": "Code", "args": { "durationMS": 871.078308105469, "detail": "" } },
{ "pid": 1, "tid": 1, "ts": 12972064.453125, "dur": 870693.908691406, "ph": "X", "name": "Methods", "args": { "durationMS": 870.693908691406, "detail": "Definitions" } },
{ "pid": 1, "tid": 1, "ts": 13851605.46875, "dur": 2658.99991989136, "ph": "X", "name": "Convert", "args": { "durationMS": 2.65899991989136, "detail": "System.Diagnostics.StackTrace" } },
{ "pid": 1, "tid": 1, "ts": 13851610.3515625, "dur": 2653.80001068115, "ph": "X", "name": "Code", "args": { "durationMS": 2.65380001068115, "detail": "" } },
{ "pid": 1, "tid": 1, "ts": 13851615.234375, "dur": 2646.399974823, "ph": "X", "name": "Methods", "args": { "durationMS": 2.646399974823, "detail": "Definitions" } },
{ "pid": 1, "tid": 1, "ts": 13861669.921875, "dur": 348854.00390625, "ph": "X", "name": "Convert", "args": { "durationMS": 348.85400390625, "detail": "System.Globalization.Extensions" } },
{ "pid": 1, "tid": 1, "ts": 13861674.8046875, "dur": 348848.602294922, "ph": "X", "name": "Code", "args": { "durationMS": 348.848602294922, "detail": "" } },
{ "pid": 1, "tid": 1, "ts": 13861681.640625, "dur": 348841.094970703, "ph": "X", "name": "Methods", "args": { "durationMS": 348.841094970703, "detail": "Definitions" } },
{ "pid": 1, "tid": 1, "ts": 14233415.0390625, "dur": 122336.502075195, "ph": "X", "name": "Convert", "args": { "durationMS": 122.336502075195, "detail": "UnityEngine.TextRenderingModule" } },
{ "pid": 1, "tid": 1, "ts": 14233447.265625, "dur": 122301.902770996, "ph": "X", "name": "Code", "args": { "durationMS": 122.301902770996, "detail": "" } },
{ "pid": 1, "tid": 1, "ts": 14233475.5859375, "dur": 122274.49798584, "ph": "X", "name": "Methods", "args": { "durationMS": 122.27449798584, "detail": "Definitions" } },
{ "pid": 1, "tid": 1, "ts": 14363678.7109375, "dur": 228967.300415039, "ph": "X", "name": "Convert", "args": { "durationMS": 228.967300415039, "detail": "UnityEngine.AnimationModule" } },
{ "pid": 1, "tid": 1, "ts": 14363682.6171875, "dur": 228962.097167969, "ph": "X", "name": "Code", "args": { "durationMS": 228.962097167969, "detail": "" } },
{ "pid": 1, "tid": 1, "ts": 14363707.03125, "dur": 228937.286376953, "ph": "X", "name": "Methods", "args": { "durationMS": 228.937286376953, "detail": "Definitions" } },
{ "pid": 1, "tid": 1, "ts": 14602796.875, "dur": 55052.4024963379, "ph": "X", "name": "Convert", "args": { "durationMS": 55.0524024963379, "detail": "UnityEngine.AudioModule" } },
{ "pid": 1, "tid": 1, "ts": 14602801.7578125, "dur": 55047.5006103516, "ph": "X", "name": "Code", "args": { "durationMS": 55.0475006103516, "detail": "" } },
{ "pid": 1, "tid": 1, "ts": 14602820.3125, "dur": 55028.6979675293, "ph": "X", "name": "Methods", "args": { "durationMS": 55.0286979675293, "detail": "Definitions" } },
{ "pid": 1, "tid": 1, "ts": 14668639.6484375, "dur": 33862.7014160156, "ph": "X", "name": "Convert", "args": { "durationMS": 33.8627014160156, "detail": "UnityEngine.DirectorModule" } },
{ "pid": 1, "tid": 1, "ts": 14668645.5078125, "dur": 33856.9984436035, "ph": "X", "name": "Code", "args": { "durationMS": 33.8569984436035, "detail": "" } },
{ "pid": 1, "tid": 1, "ts": 14668654.296875, "dur": 33848.7014770508, "ph": "X", "name": "Methods", "args": { "durationMS": 33.8487014770508, "detail": "Definitions" } },
{ "pid": 1, "tid": 1, "ts": 14719092.7734375, "dur": 287114.807128906, "ph": "X", "name": "Convert", "args": { "durationMS": 287.114807128906, "detail": "UnityEngine.IMGUIModule" } },
{ "pid": 1, "tid": 1, "ts": 14719097.65625, "dur": 287109.619140625, "ph": "X", "name": "Code", "args": { "durationMS": 287.109619140625, "detail": "" } },
{ "pid": 1, "tid": 1, "ts": 14719120.1171875, "dur": 287085.479736328, "ph": "X", "name": "Methods", "args": { "durationMS": 287.085479736328, "detail": "Definitions" } },
{ "pid": 1, "tid": 1, "ts": 15015178.7109375, "dur": 59205.4023742676, "ph": "X", "name": "Convert", "args": { "durationMS": 59.2054023742676, "detail": "UnityEngine.InputLegacyModule" } },
{ "pid": 1, "tid": 1, "ts": 15015185.546875, "dur": 59199.1996765137, "ph": "X", "name": "Code", "args": { "durationMS": 59.1991996765137, "detail": "" } },
{ "pid": 1, "tid": 1, "ts": 15015198.2421875, "dur": 59185.4972839355, "ph": "X", "name": "Methods", "args": { "durationMS": 59.1854972839355, "detail": "Definitions" } },
{ "pid": 1, "tid": 1, "ts": 15085945.3125, "dur": 75524.4064331055, "ph": "X", "name": "Convert", "args": { "durationMS": 75.5244064331055, "detail": "UnityEngine.Physics2DModule" } },
{ "pid": 1, "tid": 1, "ts": 15085950.1953125, "dur": 75518.6996459961, "ph": "X", "name": "Code", "args": { "durationMS": 75.5186996459961, "detail": "" } },
{ "pid": 1, "tid": 1, "ts": 15085964.84375, "dur": 75503.0975341797, "ph": "X", "name": "Methods", "args": { "durationMS": 75.5030975341797, "detail": "Definitions" } },
{ "pid": 1, "tid": 1, "ts": 15171428.7109375, "dur": 85216.9036865234, "ph": "X", "name": "Convert", "args": { "durationMS": 85.2169036865234, "detail": "UnityEngine.PhysicsModule" } },
{ "pid": 1, "tid": 1, "ts": 15171433.59375, "dur": 85211.5020751953, "ph": "X", "name": "Code", "args": { "durationMS": 85.2115020751953, "detail": "" } },
{ "pid": 1, "tid": 1, "ts": 15171449.21875, "dur": 85194.9005126953, "ph": "X", "name": "Methods", "args": { "durationMS": 85.1949005126953, "detail": "Definitions" } },
{ "pid": 1, "tid": 1, "ts": 15267503.90625, "dur": 82210.8993530273, "ph": "X", "name": "Convert", "args": { "durationMS": 82.2108993530273, "detail": "UnityEngine.UIModule" } },
{ "pid": 1, "tid": 1, "ts": 15267510.7421875, "dur": 82205.0018310547, "ph": "X", "name": "Code", "args": { "durationMS": 82.2050018310547, "detail": "" } },
{ "pid": 1, "tid": 1, "ts": 15267532.2265625, "dur": 82181.6024780273, "ph": "X", "name": "Methods", "args": { "durationMS": 82.1816024780273, "detail": "Definitions" } },
{ "pid": 1, "tid": 1, "ts": 15359961.9140625, "dur": 2953.9999961853, "ph": "X", "name": "Convert", "args": { "durationMS": 2.9539999961853, "detail": "netstandard" } },
{ "pid": 1, "tid": 1, "ts": 15359966.796875, "dur": 2948.69995117188, "ph": "X", "name": "Code", "args": { "durationMS": 2.94869995117188, "detail": "" } },
{ "pid": 1, "tid": 1, "ts": 15359973.6328125, "dur": 2941.69998168945, "ph": "X", "name": "Methods", "args": { "durationMS": 2.94169998168945, "detail": "Definitions" } },
{ "pid": 1, "tid": 1, "ts": 15372111.328125, "dur": 495566.070556641, "ph": "X", "name": "Convert", "args": { "durationMS": 495.566070556641, "detail": "Unity.Timeline" } },
{ "pid": 1, "tid": 1, "ts": 15372116.2109375, "dur": 495561.5234375, "ph": "X", "name": "Code", "args": { "durationMS": 495.5615234375, "detail": "" } },
{ "pid": 1, "tid": 1, "ts": 15372172.8515625, "dur": 495502.288818359, "ph": "X", "name": "Methods", "args": { "durationMS": 495.502288818359, "detail": "Definitions" } },
{ "pid": 1, "tid": 1, "ts": 15876969.7265625, "dur": 1496763.54980469, "ph": "X", "name": "Convert", "args": { "durationMS": 1496.76354980469, "detail": "UnityEngine.UI" } },
{ "pid": 1, "tid": 1, "ts": 15876974.609375, "dur": 1496758.42285156, "ph": "X", "name": "Code", "args": { "durationMS": 1496.75842285156, "detail": "" } },
{ "pid": 1, "tid": 1, "ts": 15877436.5234375, "dur": 1496294.67773438, "ph": "X", "name": "Methods", "args": { "durationMS": 1496.29467773438, "detail": "Definitions" } },
{ "pid": 1, "tid": 1, "ts": 17384851.5625, "dur": 46199.3980407715, "ph": "X", "name": "Convert", "args": { "durationMS": 46.1993980407715, "detail": "UnityEngine.UnityAnalyticsModule" } },
{ "pid": 1, "tid": 1, "ts": 17384855.46875, "dur": 46193.9010620117, "ph": "X", "name": "Code", "args": { "durationMS": 46.1939010620117, "detail": "" } },
{ "pid": 1, "tid": 1, "ts": 17384867.1875, "dur": 46180.9005737305, "ph": "X", "name": "Methods", "args": { "durationMS": 46.1809005737305, "detail": "Definitions" } },
{ "pid": 1, "tid": 1, "ts": 17440201.171875, "dur": 24602.3998260498, "ph": "X", "name": "Convert", "args": { "durationMS": 24.6023998260498, "detail": "UnityEngine.UnityWebRequestModule" } },
{ "pid": 1, "tid": 1, "ts": 17440207.03125, "dur": 24596.7998504639, "ph": "X", "name": "Code", "args": { "durationMS": 24.5967998504639, "detail": "" } },
{ "pid": 1, "tid": 1, "ts": 17440216.796875, "dur": 24587.2001647949, "ph": "X", "name": "Methods", "args": { "durationMS": 24.5872001647949, "detail": "Definitions" } },
{ "pid": 1, "tid": 1, "ts": 17475468.75, "dur": 1224579.83398438, "ph": "X", "name": "Convert", "args": { "durationMS": 1224.57983398438, "detail": "Cinemachine" } },
{ "pid": 1, "tid": 1, "ts": 17475476.5625, "dur": 1224573.48632813, "ph": "X", "name": "Code", "args": { "durationMS": 1224.57348632813, "detail": "" } },
{ "pid": 1, "tid": 1, "ts": 17475593.75, "dur": 1224454.1015625, "ph": "X", "name": "Methods", "args": { "durationMS": 1224.4541015625, "detail": "Definitions" } },
{ "pid": 1, "tid": 1, "ts": 18708626.953125, "dur": 12647.6001739502, "ph": "X", "name": "Convert", "args": { "durationMS": 12.6476001739502, "detail": "UnityEngine" } },
{ "pid": 1, "tid": 1, "ts": 18708632.8125, "dur": 12641.4003372192, "ph": "X", "name": "Code", "args": { "durationMS": 12.6414003372192, "detail": "" } },
{ "pid": 1, "tid": 1, "ts": 18708640.625, "dur": 12632.5998306274, "ph": "X", "name": "Methods", "args": { "durationMS": 12.6325998306274, "detail": "Definitions" } },
{ "pid": 1, "tid": 1, "ts": 18728847.65625, "dur": 122490.303039551, "ph": "X", "name": "Convert", "args": { "durationMS": 122.490303039551, "detail": "Assembly-CSharp" } },
{ "pid": 1, "tid": 1, "ts": 18728857.421875, "dur": 122481.704711914, "ph": "X", "name": "Code", "args": { "durationMS": 122.481704711914, "detail": "" } },
{ "pid": 1, "tid": 1, "ts": 18728878.90625, "dur": 122459.403991699, "ph": "X", "name": "Methods", "args": { "durationMS": 122.459403991699, "detail": "Definitions" } },
{ "pid": 1, "tid": 1, "ts": 18851349.609375, "dur": 9673387.6953125, "ph": "X", "name": "WriteGenerics", "args": { "durationMS": 9673.3876953125, "detail": "" } },
{ "pid": 1, "tid": 1, "ts": 19254455.078125, "dur": 18734.7011566162, "ph": "X", "name": "Arrays Definitions", "args": { "durationMS": 18.7347011566162, "detail": "" } },
{ "pid": 1, "tid": 1, "ts": 19273751.953125, "dur": 2607770.75195313, "ph": "X", "name": "GenericInstanceMethods", "args": { "durationMS": 2607.77075195313, "detail": "" } },
{ "pid": 1, "tid": 1, "ts": 21881523.4375, "dur": 5987504.8828125, "ph": "X", "name": "GenericInstanceTypes", "args": { "durationMS": 5987.5048828125, "detail": "" } },
{ "pid": 1, "tid": 1, "ts": 27869347.65625, "dur": 655374.084472656, "ph": "X", "name": "GenericComDefinitions", "args": { "durationMS": 655.374084472656, "detail": "" } },
{ "pid": 1, "tid": 1, "ts": 28545371.09375, "dur": 859.099984169006, "ph": "X", "name": "Executable Processing", "args": { "durationMS": 0.859099984169006, "detail": "" } },
{ "pid": 1, "tid": 1, "ts": 28553677.734375, "dur": 1019704.65087891, "ph": "X", "name": "MetadataCollector", "args": { "durationMS": 1019.70465087891, "detail": "" } },
{ "pid": 1, "tid": 1, "ts": 28558421.875, "dur": 31135.6983184814, "ph": "X", "name": "UpdateEmptyTokens", "args": { "durationMS": 31.1356983184814, "detail": "" } },
{ "pid": 1, "tid": 1, "ts": 28594751.953125, "dur": 43489.9024963379, "ph": "X", "name": "ValidateTokens", "args": { "durationMS": 43.4899024963379, "detail": "" } },
{ "pid": 1, "tid": 1, "ts": 29573775.390625, "dur": 5924.79991912842, "ph": "X", "name": "Write COM Callable Wrappers", "args": { "durationMS": 5.92479991912842, "detail": "" } },
{ "pid": 1, "tid": 1, "ts": 29578824.21875, "dur": 873.499989509583, "ph": "X", "name": "Collect implemented projected interfaces by COM Callable Wrappers", "args": { "durationMS": 0.873499989509583, "detail": "" } },
{ "pid": 1, "tid": 1, "ts": 29579703.125, "dur": 10101875, "ph": "X", "name": "Metadata", "args": { "durationMS": 10101.875, "detail": "Global" } },
{ "pid": 1, "tid": 1, "ts": 29714720.703125, "dur": 1274697.38769531, "ph": "X", "name": "Attributes", "args": { "durationMS": 1274.69738769531, "detail": "" } },
{ "pid": 1, "tid": 1, "ts": 31718683.59375, "dur": 2968444.82421875, "ph": "X", "name": "WriteCodeRegistration", "args": { "durationMS": 2968.44482421875, "detail": "" } },
{ "pid": 1, "tid": 1, "ts": 31861833.984375, "dur": 24359.9014282227, "ph": "X", "name": "GenericContextCollector", "args": { "durationMS": 24.3599014282227, "detail": "Collect" } },
{ "pid": 1, "tid": 1, "ts": 33521144.53125, "dur": 960.900008678436, "ph": "X", "name": "GenericContextCollector", "args": { "durationMS": 0.960900008678436, "detail": "Collect" } },
{ "pid": 1, "tid": 1, "ts": 33769238.28125, "dur": 335.599988698959, "ph": "X", "name": "GenericContextCollector", "args": { "durationMS": 0.335599988698959, "detail": "Collect" } },
{ "pid": 1, "tid": 1, "ts": 33834480.46875, "dur": 939.800024032593, "ph": "X", "name": "GenericContextCollector", "args": { "durationMS": 0.939800024032593, "detail": "Collect" } },
{ "pid": 1, "tid": 1, "ts": 33976011.71875, "dur": 11407.9999923706, "ph": "X", "name": "ReversePInvokerWrapperTable", "args": { "durationMS": 11.4079999923706, "detail": "Il2CppReversePInvokeWrapperTable.cpp" } },
{ "pid": 1, "tid": 1, "ts": 33988421.875, "dur": 354129.8828125, "ph": "X", "name": "GenericMethodPointerTable", "args": { "durationMS": 354.1298828125, "detail": "Il2CppGenericMethodPointerTable.cpp" } },
{ "pid": 1, "tid": 1, "ts": 34343101.5625, "dur": 236468.399047852, "ph": "X", "name": "InvokerTable", "args": { "durationMS": 236.468399047852, "detail": "Il2CppInvokerTable.cpp" } },
{ "pid": 1, "tid": 1, "ts": 34581808.59375, "dur": 72223.6022949219, "ph": "X", "name": "InteropDataTable", "args": { "durationMS": 72.2236022949219, "detail": "Il2CppInteropDataTable.cpp" } },
{ "pid": 1, "tid": 1, "ts": 34687128.90625, "dur": 4994446.2890625, "ph": "X", "name": "WriteMetadata", "args": { "durationMS": 4994.4462890625, "detail": "" } },
{ "pid": 1, "tid": 1, "ts": 34947246.09375, "dur": 6808.59994888306, "ph": "X", "name": "Metadata", "args": { "durationMS": 6.80859994888306, "detail": "Collect string literals" } },
{ "pid": 1, "tid": 1, "ts": 35420835.9375, "dur": 265839.996337891, "ph": "X", "name": "GenericClasses", "args": { "durationMS": 265.839996337891, "detail": "" } },
{ "pid": 1, "tid": 1, "ts": 35686675.78125, "dur": 93448.1048583984, "ph": "X", "name": "GenericInst2", "args": { "durationMS": 93.4481048583984, "detail": "" } },
{ "pid": 1, "tid": 1, "ts": 35780125, "dur": 613500.610351563, "ph": "X", "name": "GenericMethods", "args": { "durationMS": 613.500610351563, "detail": "" } },
{ "pid": 1, "tid": 1, "ts": 36393625, "dur": 582897.399902344, "ph": "X", "name": "Il2CppTypes", "args": { "durationMS": 582.897399902344, "detail": "" } },
{ "pid": 1, "tid": 1, "ts": 36976523.4375, "dur": 130472.808837891, "ph": "X", "name": "GenericMethods", "args": { "durationMS": 130.472808837891, "detail": "" } },
{ "pid": 1, "tid": 1, "ts": 37106996.09375, "dur": 1634651.73339844, "ph": "X", "name": "CompilerCalculateTypeValues", "args": { "durationMS": 1634.65173339844, "detail": "" } },
{ "pid": 1, "tid": 1, "ts": 38741652.34375, "dur": 188872.299194336, "ph": "X", "name": "Registration", "args": { "durationMS": 188.872299194336, "detail": "" } },
{ "pid": 1, "tid": 1, "ts": 38931421.875, "dur": 10505.9995651245, "ph": "X", "name": "StringLiteralWriter", "args": { "durationMS": 10.5059995651245, "detail": "" } },
{ "pid": 1, "tid": 1, "ts": 38942328.125, "dur": 2765.79999923706, "ph": "X", "name": "Metadata Strings", "args": { "durationMS": 2.76579999923706, "detail": "" } },
{ "pid": 1, "tid": 1, "ts": 38945097.65625, "dur": 4803.59983444214, "ph": "X", "name": "Events", "args": { "durationMS": 4.80359983444214, "detail": "" } },
{ "pid": 1, "tid": 1, "ts": 38949902.34375, "dur": 9088.80043029785, "ph": "X", "name": "Properties", "args": { "durationMS": 9.08880043029785, "detail": "" } },
{ "pid": 1, "tid": 1, "ts": 38958992.1875, "dur": 136209.30480957, "ph": "X", "name": "Methods", "args": { "durationMS": 136.20930480957, "detail": "" } },
{ "pid": 1, "tid": 1, "ts": 39095203.125, "dur": 2268.39995384216, "ph": "X", "name": "Parameter Default Values", "args": { "durationMS": 2.26839995384216, "detail": "" } },
{ "pid": 1, "tid": 1, "ts": 39097472.65625, "dur": 3328.90009880066, "ph": "X", "name": "Field Default Values", "args": { "durationMS": 3.32890009880066, "detail": "" } },
{ "pid": 1, "tid": 1, "ts": 39100800.78125, "dur": 1090.0000333786, "ph": "X", "name": "Field and Parameter Default Values Data", "args": { "durationMS": 1.0900000333786, "detail": "" } },
{ "pid": 1, "tid": 1, "ts": 39101894.53125, "dur": 1480.299949646, "ph": "X", "name": "Field Marshaled Sizes", "args": { "durationMS": 1.480299949646, "detail": "" } },
{ "pid": 1, "tid": 1, "ts": 39103375, "dur": 27906.400680542, "ph": "X", "name": "Parameters", "args": { "durationMS": 27.906400680542, "detail": "" } },
{ "pid": 1, "tid": 1, "ts": 39131285.15625, "dur": 25226.6006469727, "ph": "X", "name": "Fields", "args": { "durationMS": 25.2266006469727, "detail": "" } },
{ "pid": 1, "tid": 1, "ts": 39156511.71875, "dur": 3697.79992103577, "ph": "X", "name": "Generic Parameters", "args": { "durationMS": 3.69779992103577, "detail": "" } },
{ "pid": 1, "tid": 1, "ts": 39160210.9375, "dur": 1108.00004005432, "ph": "X", "name": "Generic Parameter Constraints", "args": { "durationMS": 1.10800004005432, "detail": "" } },
{ "pid": 1, "tid": 1, "ts": 39161320.3125, "dur": 3339.60008621216, "ph": "X", "name": "Generic Containers", "args": { "durationMS": 3.33960008621216, "detail": "" } },
{ "pid": 1, "tid": 1, "ts": 39164660.15625, "dur": 1072.19994068146, "ph": "X", "name": "Nested Types", "args": { "durationMS": 1.07219994068146, "detail": "" } },
{ "pid": 1, "tid": 1, "ts": 39165734.375, "dur": 731.899976730347, "ph": "X", "name": "Interfaces", "args": { "durationMS": 0.731899976730347, "detail": "" } },
{ "pid": 1, "tid": 1, "ts": 39166464.84375, "dur": 295300.811767578, "ph": "X", "name": "VTables", "args": { "durationMS": 295.300811767578, "detail": "" } },
{ "pid": 1, "tid": 1, "ts": 39461769.53125, "dur": 29401.798248291, "ph": "X", "name": "Interface Offsets", "args": { "durationMS": 29.401798248291, "detail": "" } },
{ "pid": 1, "tid": 1, "ts": 39491175.78125, "dur": 114975.708007813, "ph": "X", "name": "Type Definitions", "args": { "durationMS": 114.975708007813, "detail": "" } },
{ "pid": 1, "tid": 1, "ts": 39606152.34375, "dur": 10512.1002197266, "ph": "X", "name": "Images", "args": { "durationMS": 10.5121002197266, "detail": "" } },
{ "pid": 1, "tid": 1, "ts": 39616664.0625, "dur": 6423.90012741089, "ph": "X", "name": "Assemblies", "args": { "durationMS": 6.42390012741089, "detail": "" } },
{ "pid": 1, "tid": 1, "ts": 39623089.84375, "dur": 3332.00001716614, "ph": "X", "name": "Metadata Usage Lists", "args": { "durationMS": 3.33200001716614, "detail": "" } },
{ "pid": 1, "tid": 1, "ts": 39626421.875, "dur": 7160.09998321533, "ph": "X", "name": "Metadata Usage Pairs", "args": { "durationMS": 7.16009998321533, "detail": "" } },
{ "pid": 1, "tid": 1, "ts": 39633585.9375, "dur": 689.599990844727, "ph": "X", "name": "Field Refs", "args": { "durationMS": 0.689599990844727, "detail": "" } },
{ "pid": 1, "tid": 1, "ts": 39634277.34375, "dur": 699.599981307983, "ph": "X", "name": "Referenced Assemblies", "args": { "durationMS": 0.699599981307983, "detail": "" } },
{ "pid": 1, "tid": 1, "ts": 39634976.5625, "dur": 5530.20000457764, "ph": "X", "name": "Attribute Types Ranges", "args": { "durationMS": 5.53020000457764, "detail": "" } },
{ "pid": 1, "tid": 1, "ts": 39640503.90625, "dur": 1172.99997806549, "ph": "X", "name": "Attribute Types", "args": { "durationMS": 1.17299997806549, "detail": "" } },
{ "pid": 1, "tid": 1, "ts": 39641679.6875, "dur": 794.600009918213, "ph": "X", "name": "Unresolved Virtual Call Parameter Types", "args": { "durationMS": 0.794600009918213, "detail": "" } },
{ "pid": 1, "tid": 1, "ts": 39642476.5625, "dur": 2441.49994850159, "ph": "X", "name": "Unresolved Virtual Call Parameter Ranges", "args": { "durationMS": 2.44149994850159, "detail": "" } },
{ "pid": 1, "tid": 1, "ts": 39644917.96875, "dur": 1210.70003509521, "ph": "X", "name": "Windows Runtime type names", "args": { "durationMS": 1.21070003509521, "detail": "" } },
{ "pid": 1, "tid": 1, "ts": 39646132.8125, "dur": 2588.90008926392, "ph": "X", "name": "Exported Types", "args": { "durationMS": 2.58890008926392, "detail": "" } },
{ "pid": 1, "tid": 1, "ts": 40816800.78125, "dur": 91655625, "ph": "X", "name": "Build", "args": { "durationMS": 91655.625, "detail": "" } },
{ "pid": 1, "tid": 1, "ts": 40825449.21875, "dur": 91644648.4375, "ph": "X", "name": "BuildBinary", "args": { "durationMS": 91644.6484375, "detail": "" } },
{ "pid": 1, "tid": 1, "ts": 40826019.53125, "dur": 344419.494628906, "ph": "X", "name": "FindFilesToCompile", "args": { "durationMS": 344.419494628906, "detail": "" } },
{ "pid": 1, "tid": 1, "ts": 41170445.3125, "dur": 1367279.66308594, "ph": "X", "name": "Calculate header hashes", "args": { "durationMS": 1367.27966308594, "detail": "" } },
{ "pid": 1, "tid": 1, "ts": 41179183.59375, "dur": 1124031.73828125, "ph": "X", "name": "HashOfAllFilesWithProviderExtensionInDirectory", "args": { "durationMS": 1124.03173828125, "detail": "C:\\Program Files\\Unity\\Hub\\Editor\\2019.2.16f1\\Editor\\Data\\il2cpp\\libil2cpp" } },
{ "pid": 1, "tid": 1, "ts": 42303480.46875, "dur": 83432.1060180664, "ph": "X", "name": "HashOfAllFilesWithProviderExtensionInDirectory", "args": { "durationMS": 83.4321060180664, "detail": "C:\\Program Files\\Unity\\Hub\\Editor\\2019.2.16f1\\Editor\\Data\\il2cpp\\external\\bdwgc\\include" } },
{ "pid": 1, "tid": 1, "ts": 42387058.59375, "dur": 31579.0023803711, "ph": "X", "name": "HashOfAllFilesWithProviderExtensionInDirectory", "args": { "durationMS": 31.5790023803711, "detail": "C:\\Program Files\\Unity\\Hub\\Editor\\2019.2.16f1\\Editor\\Data\\il2cpp\\external\\xxHash" } },
{ "pid": 1, "tid": 1, "ts": 42418785.15625, "dur": 10321.1002349854, "ph": "X", "name": "HashOfAllFilesWithProviderExtensionInDirectory", "args": { "durationMS": 10.3211002349854, "detail": "C:\\Users\\Marti\\Documents\\GitHub\\RPG-201920\\rpg_201920\\Temp\\StagingArea\\Data\\il2cppOutput" } },
{ "pid": 1, "tid": 1, "ts": 42474531.25, "dur": 55827.8961181641, "ph": "X", "name": "HashOfAllFilesWithProviderExtensionInDirectory", "args": { "durationMS": 55.8278961181641, "detail": "C:\\Program Files\\Unity\\Hub\\Editor\\2019.2.16f1\\Editor\\Data\\il2cpp\\external\\bdwgc\\libatomic_ops\\src" } },
{ "pid": 1, "tid": 1, "ts": 42537722.65625, "dur": 1334576.90429688, "ph": "X", "name": "Calculate lumped hashes", "args": { "durationMS": 1334.57690429688, "detail": "" } },
{ "pid": 1, "tid": 1, "ts": 42540589.84375, "dur": 4958.00018310547, "ph": "X", "name": "HashOfAllFilesWithProviderExtensionInDirectory", "args": { "durationMS": 4.95800018310547, "detail": "C:\\Program Files\\Unity\\Hub\\Editor\\2019.2.16f1\\Editor\\Data\\il2cpp\\libil2cpp\\codegen" } },
{ "pid": 1, "tid": 1, "ts": 42545671.875, "dur": 30431.2992095947, "ph": "X", "name": "HashOfAllFilesWithProviderExtensionInDirectory", "args": { "durationMS": 30.4312992095947, "detail": "C:\\Program Files\\Unity\\Hub\\Editor\\2019.2.16f1\\Editor\\Data\\il2cpp\\libil2cpp\\debugger" } },
{ "pid": 1, "tid": 1, "ts": 42576312.5, "dur": 13004.1999816895, "ph": "X", "name": "HashOfAllFilesWithProviderExtensionInDirectory", "args": { "durationMS": 13.0041999816895, "detail": "C:\\Program Files\\Unity\\Hub\\Editor\\2019.2.16f1\\Editor\\Data\\il2cpp\\libil2cpp\\gc" } },
{ "pid": 1, "tid": 1, "ts": 42589449.21875, "dur": 419713.195800781, "ph": "X", "name": "HashOfAllFilesWithProviderExtensionInDirectory", "args": { "durationMS": 419.713195800781, "detail": "C:\\Program Files\\Unity\\Hub\\Editor\\2019.2.16f1\\Editor\\Data\\il2cpp\\libil2cpp\\icalls" } },
{ "pid": 1, "tid": 1, "ts": 43009304.6875, "dur": 60407.8025817871, "ph": "X", "name": "HashOfAllFilesWithProviderExtensionInDirectory", "args": { "durationMS": 60.4078025817871, "detail": "C:\\Program Files\\Unity\\Hub\\Editor\\2019.2.16f1\\Editor\\Data\\il2cpp\\libil2cpp\\metadata" } },
{ "pid": 1, "tid": 1, "ts": 43069855.46875, "dur": 6691.50018692017, "ph": "X", "name": "HashOfAllFilesWithProviderExtensionInDirectory", "args": { "durationMS": 6.69150018692017, "detail": "C:\\Program Files\\Unity\\Hub\\Editor\\2019.2.16f1\\Editor\\Data\\il2cpp\\libil2cpp\\mono" } },
{ "pid": 1, "tid": 1, "ts": 43076683.59375, "dur": 2913.30003738403, "ph": "X", "name": "HashOfAllFilesWithProviderExtensionInDirectory", "args": { "durationMS": 2.91330003738403, "detail": "C:\\Program Files\\Unity\\Hub\\Editor\\2019.2.16f1\\Editor\\Data\\il2cpp\\libil2cpp\\mono-runtime" } },
{ "pid": 1, "tid": 1, "ts": 43079718.75, "dur": 406282.104492188, "ph": "X", "name": "HashOfAllFilesWithProviderExtensionInDirectory", "args": { "durationMS": 406.282104492188, "detail": "C:\\Program Files\\Unity\\Hub\\Editor\\2019.2.16f1\\Editor\\Data\\il2cpp\\libil2cpp\\os" } },
{ "pid": 1, "tid": 1, "ts": 43486144.53125, "dur": 11242.600440979, "ph": "X", "name": "HashOfAllFilesWithProviderExtensionInDirectory", "args": { "durationMS": 11.242600440979, "detail": "C:\\Program Files\\Unity\\Hub\\Editor\\2019.2.16f1\\Editor\\Data\\il2cpp\\libil2cpp\\utils" } },
{ "pid": 1, "tid": 1, "ts": 43497578.125, "dur": 49108.4976196289, "ph": "X", "name": "HashOfAllFilesWithProviderExtensionInDirectory", "args": { "durationMS": 49.1084976196289, "detail": "C:\\Program Files\\Unity\\Hub\\Editor\\2019.2.16f1\\Editor\\Data\\il2cpp\\libil2cpp\\vm" } },
{ "pid": 1, "tid": 1, "ts": 43546820.3125, "dur": 4427.99997329712, "ph": "X", "name": "HashOfAllFilesWithProviderExtensionInDirectory", "args": { "durationMS": 4.42799997329712, "detail": "C:\\Program Files\\Unity\\Hub\\Editor\\2019.2.16f1\\Editor\\Data\\il2cpp\\libil2cpp\\vm-utils" } },
{ "pid": 1, "tid": 1, "ts": 43551386.71875, "dur": 320887.908935547, "ph": "X", "name": "HashOfAllFilesWithProviderExtensionInDirectory", "args": { "durationMS": 320.887908935547, "detail": "C:\\Program Files\\Unity\\Hub\\Editor\\2019.2.16f1\\Editor\\Data\\il2cpp\\external\\bdwgc" } },
{ "pid": 1, "tid": 1, "ts": 43872300.78125, "dur": 19985982.421875, "ph": "X", "name": "BuildAllCppFiles", "args": { "durationMS": 19985.982421875, "detail": "" } },
{ "pid": 1, "tid": 1, "ts": 43951453.125, "dur": 19906828.125, "ph": "X", "name": "Compile", "args": { "durationMS": 19906.828125, "detail": "" } },
{ "pid": 1, "tid": 1, "ts": 63858285.15625, "dur": 980.000019073486, "ph": "X", "name": "OnBeforeLink Build", "args": { "durationMS": 0.980000019073486, "detail": "" } },
{ "pid": 1, "tid": 1, "ts": 63858867.1875, "dur": 394.300013780594, "ph": "X", "name": "ProgramBuildDescription OnBeforeLink Build", "args": { "durationMS": 0.394300013780594, "detail": "" } },
{ "pid": 1, "tid": 1, "ts": 63859261.71875, "dur": 66316187.5, "ph": "X", "name": "Postprocess Object Files", "args": { "durationMS": 66316.1875, "detail": "" } },
{ "pid": 1, "tid": 1, "ts": 63862339.84375, "dur": 66313109.375, "ph": "X", "name": "Link", "args": { "durationMS": 66313.109375, "detail": "build.bc" } },
{ "pid": 1, "tid": 1, "ts": 63895949.21875, "dur": 2130704.34570313, "ph": "X", "name": "hash linker invocation", "args": { "durationMS": 2130.70434570313, "detail": "" } },
{ "pid": 1, "tid": 1, "ts": 66042007.8125, "dur": 63896722.65625, "ph": "X", "name": "ActualLinkerInvocation", "args": { "durationMS": 63896.72265625, "detail": "build.bc" } },
{ "pid": 1, "tid": 1, "ts": 130175453.125, "dur": 2112298.828125, "ph": "X", "name": "ProgramDescription Finalize Build", "args": { "durationMS": 2112.298828125, "detail": "" } },
{ "pid": 1, "tid": 1, "ts": 132287890.625, "dur": 182217.102050781, "ph": "X", "name": "Clean IL2CPP Cache", "args": { "durationMS": 182.217102050781, "detail": "" } },
{ "pid": 1, "tid": 7, "ph": "M", "name": "thread_name", "args": { "name": "" } },
{ "pid": 1, "tid": 7, "ts": 44023792.96875, "dur": 66581.4971923828, "ph": "X", "name": "HashCompilerInvocation", "args": { "durationMS": 66.5814971923828, "detail": "Il2CppAttributes.cpp" } },
{ "pid": 1, "tid": 7, "ts": 44091351.5625, "dur": 16530.3001403809, "ph": "X", "name": "HashCompilerInvocation", "args": { "durationMS": 16.5303001403809, "detail": "Il2CppInvokerTable.cpp" } },
{ "pid": 1, "tid": 7, "ts": 44108625, "dur": 9747.30014801025, "ph": "X", "name": "HashCompilerInvocation", "args": { "durationMS": 9.74730014801025, "detail": "mscorlib4.cpp" } },
{ "pid": 1, "tid": 7, "ts": 44118910.15625, "dur": 10669.3000793457, "ph": "X", "name": "HashCompilerInvocation", "args": { "durationMS": 10.6693000793457, "detail": "GenericMethods.cpp" } },
{ "pid": 1, "tid": 7, "ts": 44129988.28125, "dur": 11814.8002624512, "ph": "X", "name": "HashCompilerInvocation", "args": { "durationMS": 11.8148002624512, "detail": "mscorlib11.cpp" } },
{ "pid": 1, "tid": 7, "ts": 44142335.9375, "dur": 8137.10021972656, "ph": "X", "name": "HashCompilerInvocation", "args": { "durationMS": 8.13710021972656, "detail": "mscorlib12.cpp" } },
{ "pid": 1, "tid": 7, "ts": 44150984.375, "dur": 9282.89985656738, "ph": "X", "name": "HashCompilerInvocation", "args": { "durationMS": 9.28289985656738, "detail": "UnityEngine.UI1.cpp" } },
{ "pid": 1, "tid": 7, "ts": 44160796.875, "dur": 8668.39981079102, "ph": "X", "name": "HashCompilerInvocation", "args": { "durationMS": 8.66839981079102, "detail": "System.cpp" } },
{ "pid": 1, "tid": 7, "ts": 44170007.8125, "dur": 8899.29962158203, "ph": "X", "name": "HashCompilerInvocation", "args": { "durationMS": 8.89929962158203, "detail": "mscorlib15.cpp" } },
{ "pid": 1, "tid": 7, "ts": 44179335.9375, "dur": 14070.1999664307, "ph": "X", "name": "HashCompilerInvocation", "args": { "durationMS": 14.0701999664307, "detail": "Il2CppGenericMethodDefinitions.c" } },
{ "pid": 1, "tid": 7, "ts": 44193906.25, "dur": 8308.79974365234, "ph": "X", "name": "HashCompilerInvocation", "args": { "durationMS": 8.30879974365234, "detail": "Unity.Timeline.cpp" } },
{ "pid": 1, "tid": 7, "ts": 44202667.96875, "dur": 12126.5001296997, "ph": "X", "name": "HashCompilerInvocation", "args": { "durationMS": 12.1265001296997, "detail": "UnityEngine.CoreModule1.cpp" } },
{ "pid": 1, "tid": 7, "ts": 44215218.75, "dur": 5951.70021057129, "ph": "X", "name": "HashCompilerInvocation", "args": { "durationMS": 5.95170021057129, "detail": "Generics8.cpp" } },
{ "pid": 1, "tid": 7, "ts": 44221597.65625, "dur": 5393.79978179932, "ph": "X", "name": "HashCompilerInvocation", "args": { "durationMS": 5.39379978179932, "detail": "GenericMethods1.cpp" } },
{ "pid": 1, "tid": 7, "ts": 44227453.125, "dur": 5901.80015563965, "ph": "X", "name": "HashCompilerInvocation", "args": { "durationMS": 5.90180015563965, "detail": "mscorlib17.cpp" } },
{ "pid": 1, "tid": 7, "ts": 44233777.34375, "dur": 2966.00008010864, "ph": "X", "name": "HashCompilerInvocation", "args": { "durationMS": 2.96600008010864, "detail": "UnityEngine.UI_CodeGen.c" } },
{ "pid": 1, "tid": 7, "ts": 44237179.6875, "dur": 2814.59999084473, "ph": "X", "name": "HashCompilerInvocation", "args": { "durationMS": 2.81459999084473, "detail": "Cinemachine2.cpp" } },
{ "pid": 1, "tid": 7, "ts": 44240445.3125, "dur": 1340.29996395111, "ph": "X", "name": "HashCompilerInvocation", "args": { "durationMS": 1.34029996395111, "detail": "Cinemachine_CodeGen.c" } },
{ "pid": 1, "tid": 7, "ts": 44242093.75, "dur": 1643.70000362396, "ph": "X", "name": "HashCompilerInvocation", "args": { "durationMS": 1.64370000362396, "detail": "UnityEngine.TextRenderingModule.cpp" } },
{ "pid": 1, "tid": 7, "ts": 44244066.40625, "dur": 1251.99997425079, "ph": "X", "name": "HashCompilerInvocation", "args": { "durationMS": 1.25199997425079, "detail": "UnityEngine.InputLegacyModule.cpp" } },
{ "pid": 1, "tid": 7, "ts": 44245726.5625, "dur": 1848.50001335144, "ph": "X", "name": "HashCompilerInvocation", "args": { "durationMS": 1.84850001335144, "detail": "Unity.Timeline_CodeGen.c" } },
{ "pid": 1, "tid": 7, "ts": 44248011.71875, "dur": 10429.9001693726, "ph": "X", "name": "HashCompilerInvocation", "args": { "durationMS": 10.4299001693726, "detail": "UnityICallRegistration.cpp" } },
{ "pid": 1, "tid": 7, "ts": 44258816.40625, "dur": 724.09999370575, "ph": "X", "name": "HashCompilerInvocation", "args": { "durationMS": 0.72409999370575, "detail": "UnityEngine.UnityAnalyticsModule.cpp" } },
{ "pid": 1, "tid": 7, "ts": 44259863.28125, "dur": 1207.49998092651, "ph": "X", "name": "HashCompilerInvocation", "args": { "durationMS": 1.20749998092651, "detail": "System.Configuration.cpp" } },
{ "pid": 1, "tid": 7, "ts": 44261414.0625, "dur": 769.900023937225, "ph": "X", "name": "HashCompilerInvocation", "args": { "durationMS": 0.769900023937225, "detail": "UnityEngine.DirectorModule.cpp" } },
{ "pid": 1, "tid": 7, "ts": 44262460.9375, "dur": 41186.5997314453, "ph": "X", "name": "HashCompilerInvocation", "args": { "durationMS": 41.1865997314453, "detail": "il2cpp-api.cpp" } },
{ "pid": 1, "tid": 7, "ts": 44304332.03125, "dur": 1128.00002098083, "ph": "X", "name": "HashCompilerInvocation", "args": { "durationMS": 1.12800002098083, "detail": "System.Core.cpp" } },
{ "pid": 1, "tid": 7, "ts": 44305964.84375, "dur": 33834.098815918, "ph": "X", "name": "HashCompilerInvocation", "args": { "durationMS": 33.834098815918, "detail": "gzread.c" } },
{ "pid": 1, "tid": 7, "ts": 44340171.875, "dur": 22189.6991729736, "ph": "X", "name": "HashCompilerInvocation", "args": { "durationMS": 22.1896991729736, "detail": "crc32.c" } },
{ "pid": 1, "tid": 7, "ts": 44363160.15625, "dur": 1151.60000324249, "ph": "X", "name": "HashCompilerInvocation", "args": { "durationMS": 1.15160000324249, "detail": "System.Core_CodeGen.c" } },
{ "pid": 1, "tid": 7, "ts": 44364707.03125, "dur": 1248.39997291565, "ph": "X", "name": "HashCompilerInvocation", "args": { "durationMS": 1.24839997291565, "detail": "System.Xml.cpp" } },
{ "pid": 1, "tid": 7, "ts": 44366335.9375, "dur": 842.199981212616, "ph": "X", "name": "HashCompilerInvocation", "args": { "durationMS": 0.842199981212616, "detail": "Lump_libil2cpp_vm.cpp" } },
{ "pid": 1, "tid": 7, "ts": 44368105.46875, "dur": 752.20000743866, "ph": "X", "name": "HashCompilerInvocation", "args": { "durationMS": 0.75220000743866, "detail": "UnityEngine.DirectorModule_CodeGen.c" } },
{ "pid": 1, "tid": 7, "ts": 44369375, "dur": 4677.70004272461, "ph": "X", "name": "HashCompilerInvocation", "args": { "durationMS": 4.67770004272461, "detail": "gc.c" } },
{ "pid": 1, "tid": 7, "ts": 44374417.96875, "dur": 660.49998998642, "ph": "X", "name": "HashCompilerInvocation", "args": { "durationMS": 0.66049998998642, "detail": "Lump_libil2cpp_metadata.cpp" } },
{ "pid": 1, "tid": 7, "ts": 44375410.15625, "dur": 622.500002384186, "ph": "X", "name": "HashCompilerInvocation", "args": { "durationMS": 0.622500002384186, "detail": "Lump_libil2cpp_utils.cpp" } },
{ "pid": 1, "tid": 7, "ts": 44376363.28125, "dur": 919.49999332428, "ph": "X", "name": "HashCompilerInvocation", "args": { "durationMS": 0.91949999332428, "detail": "krait_signal_handler.c" } },
{ "pid": 1, "tid": 7, "ts": 44377625, "dur": 617.500007152557, "ph": "X", "name": "HashCompilerInvocation", "args": { "durationMS": 0.617500007152557, "detail": "Il2CppMetadataRegistration.c" } },
{ "pid": 1, "tid": 7, "ts": 44378562.5, "dur": 584.699988365173, "ph": "X", "name": "HashCompilerInvocation", "args": { "durationMS": 0.584699988365173, "detail": "netstandard.cpp" } },
{ "pid": 1, "tid": 7, "ts": 44379468.75, "dur": 586.099982261658, "ph": "X", "name": "HashCompilerInvocation", "args": { "durationMS": 0.586099982261658, "detail": "System.Diagnostics.StackTrace.cpp" } },
{ "pid": 1, "tid": 7, "ts": 44380496.09375, "dur": 612.600028514862, "ph": "X", "name": "HashCompilerInvocation", "args": { "durationMS": 0.612600028514862, "detail": "System.Globalization.Extensions.cpp" } },
{ "pid": 1, "tid": 7, "ts": 44381437.5, "dur": 1164.10005092621, "ph": "X", "name": "HashCompilerInvocation", "args": { "durationMS": 1.16410005092621, "detail": "Lump_libil2cpp_mono.cpp" } },
{ "pid": 1, "tid": 7, "ts": 44382968.75, "dur": 1508.90004634857, "ph": "X", "name": "HashCompilerInvocation", "args": { "durationMS": 1.50890004634857, "detail": "gzclose.c" } },
{ "pid": 1, "tid": 7, "ts": 44384960.9375, "dur": 1076.79998874664, "ph": "X", "name": "HashCompilerInvocation", "args": { "durationMS": 1.07679998874664, "detail": "Lump_libil2cpp_vm-utils.cpp" } },
{ "pid": 1, "tid": 7, "ts": 44386375, "dur": 631.399989128113, "ph": "X", "name": "HashCompilerInvocation", "args": { "durationMS": 0.631399989128113, "detail": "System.Diagnostics.StackTrace_CodeGen.c" } },
{ "pid": 1, "tid": 7, "ts": 44387339.84375, "dur": 985.300004482269, "ph": "X", "name": "HashCompilerInvocation", "args": { "durationMS": 0.985300004482269, "detail": "UnityEngine_CodeGen.c" } },
{ "pid": 1, "tid": 7, "ts": 44388667.96875, "dur": 611.000001430511, "ph": "X", "name": "HashCompilerInvocation", "args": { "durationMS": 0.611000001430511, "detail": "Lump_libil2cpp_codegen.cpp" } },
{ "pid": 1, "tid": 7, "ts": 44389605.46875, "dur": 627.600014209747, "ph": "X", "name": "HashCompilerInvocation", "args": { "durationMS": 0.627600014209747, "detail": "Lump_libil2cpp_debugger.cpp" } },
{ "pid": 1, "tid": 5, "ph": "M", "name": "thread_name", "args": { "name": "" } },
{ "pid": 1, "tid": 5, "ts": 44023812.5, "dur": 66729.4998168945, "ph": "X", "name": "HashCompilerInvocation", "args": { "durationMS": 66.7294998168945, "detail": "Il2CppCompilerCalculateTypeValues.cpp" } },
{ "pid": 1, "tid": 5, "ts": 44091359.375, "dur": 13360.8999252319, "ph": "X", "name": "HashCompilerInvocation", "args": { "durationMS": 13.3608999252319, "detail": "mscorlib_CodeGen.c" } },
{ "pid": 1, "tid": 5, "ts": 44105414.0625, "dur": 12719.9001312256, "ph": "X", "name": "HashCompilerInvocation", "args": { "durationMS": 12.7199001312256, "detail": "Il2CppGenericMethodPointerTable.cpp" } },
{ "pid": 1, "tid": 5, "ts": 44118910.15625, "dur": 9359.90047454834, "ph": "X", "name": "HashCompilerInvocation", "args": { "durationMS": 9.35990047454834, "detail": "mscorlib.cpp" } },
{ "pid": 1, "tid": 5, "ts": 44128710.9375, "dur": 14202.7006149292, "ph": "X", "name": "HashCompilerInvocation", "args": { "durationMS": 14.2027006149292, "detail": "Cinemachine1.cpp" } },
{ "pid": 1, "tid": 5, "ts": 44143343.75, "dur": 9081.99977874756, "ph": "X", "name": "HashCompilerInvocation", "args": { "durationMS": 9.08199977874756, "detail": "mscorlib16.cpp" } },
{ "pid": 1, "tid": 5, "ts": 44153398.4375, "dur": 7737.29991912842, "ph": "X", "name": "HashCompilerInvocation", "args": { "durationMS": 7.73729991912842, "detail": "GenericMethods2.cpp" } },
{ "pid": 1, "tid": 5, "ts": 44162472.65625, "dur": 7622.49994277954, "ph": "X", "name": "HashCompilerInvocation", "args": { "durationMS": 7.62249994277954, "detail": "UnityEngine.UI2.cpp" } },
{ "pid": 1, "tid": 5, "ts": 44172410.15625, "dur": 8235.09979248047, "ph": "X", "name": "HashCompilerInvocation", "args": { "durationMS": 8.23509979248047, "detail": "GenericMethods3.cpp" } },
{ "pid": 1, "tid": 5, "ts": 44181085.9375, "dur": 7958.00018310547, "ph": "X", "name": "HashCompilerInvocation", "args": { "durationMS": 7.95800018310547, "detail": "mscorlib8.cpp" } },
{ "pid": 1, "tid": 5, "ts": 44189464.84375, "dur": 6988.59977722168, "ph": "X", "name": "HashCompilerInvocation", "args": { "durationMS": 6.98859977722168, "detail": "mscorlib13.cpp" } },
{ "pid": 1, "tid": 5, "ts": 44198453.125, "dur": 6565.89984893799, "ph": "X", "name": "HashCompilerInvocation", "args": { "durationMS": 6.56589984893799, "detail": "Il2CppGenericMethodTable.c" } },
{ "pid": 1, "tid": 5, "ts": 44205449.21875, "dur": 7014.10007476807, "ph": "X", "name": "HashCompilerInvocation", "args": { "durationMS": 7.01410007476807, "detail": "Generics4.cpp" } },
{ "pid": 1, "tid": 5, "ts": 44212925.78125, "dur": 11068.699836731, "ph": "X", "name": "HashCompilerInvocation", "args": { "durationMS": 11.068699836731, "detail": "Generics12.cpp" } },
{ "pid": 1, "tid": 5, "ts": 44224421.875, "dur": 5675.60005187988, "ph": "X", "name": "HashCompilerInvocation", "args": { "durationMS": 5.67560005187988, "detail": "System1.cpp" } },
{ "pid": 1, "tid": 5, "ts": 44230527.34375, "dur": 4447.80015945435, "ph": "X", "name": "HashCompilerInvocation", "args": { "durationMS": 4.44780015945435, "detail": "UnityEngine.IMGUIModule.cpp" } },
{ "pid": 1, "tid": 5, "ts": 44235421.875, "dur": 2263.99993896484, "ph": "X", "name": "HashCompilerInvocation", "args": { "durationMS": 2.26399993896484, "detail": "UnityEngine.CoreModule_CodeGen.c" } },
{ "pid": 1, "tid": 5, "ts": 44238109.375, "dur": 2461.10010147095, "ph": "X", "name": "HashCompilerInvocation", "args": { "durationMS": 2.46110010147095, "detail": "Il2CppCompilerCalculateTypeValuesTable.cpp" } },
{ "pid": 1, "tid": 5, "ts": 44240988.28125, "dur": 1530.30002117157, "ph": "X", "name": "HashCompilerInvocation", "args": { "durationMS": 1.53030002117157, "detail": "UnityEngine.Physics2DModule.cpp" } },
{ "pid": 1, "tid": 5, "ts": 44242925.78125, "dur": 1829.80000972748, "ph": "X", "name": "HashCompilerInvocation", "args": { "durationMS": 1.82980000972748, "detail": "UnityEngine.UIModule.cpp" } },
{ "pid": 1, "tid": 5, "ts": 44245175.78125, "dur": 1891.4999961853, "ph": "X", "name": "HashCompilerInvocation", "args": { "durationMS": 1.8914999961853, "detail": "System_CodeGen.c" } },
{ "pid": 1, "tid": 5, "ts": 44247519.53125, "dur": 1677.99997329712, "ph": "X", "name": "HashCompilerInvocation", "args": { "durationMS": 1.67799997329712, "detail": "Mono.Security.cpp" } },
{ "pid": 1, "tid": 5, "ts": 44249703.125, "dur": 30576.1985778809, "ph": "X", "name": "HashCompilerInvocation", "args": { "durationMS": 30.5761985778809, "detail": "deflate.c" } },
{ "pid": 1, "tid": 5, "ts": 44280691.40625, "dur": 54747.802734375, "ph": "X", "name": "HashCompilerInvocation", "args": { "durationMS": 54.747802734375, "detail": "xamarin_getifaddrs.c" } },
{ "pid": 1, "tid": 5, "ts": 44336269.53125, "dur": 1305.29999732971, "ph": "X", "name": "HashCompilerInvocation", "args": { "durationMS": 1.30529999732971, "detail": "UnityClassRegistration.cpp" } },
{ "pid": 1, "tid": 5, "ts": 44339089.84375, "dur": 1341.79997444153, "ph": "X", "name": "HashCompilerInvocation", "args": { "durationMS": 1.34179997444153, "detail": "UnityEngine.SharedInternalsModule_CodeGen.c" } },
{ "pid": 1, "tid": 5, "ts": 44341070.3125, "dur": 1256.00004196167, "ph": "X", "name": "HashCompilerInvocation", "args": { "durationMS": 1.25600004196167, "detail": "UnityEngine.TextRenderingModule_CodeGen.c" } },
{ "pid": 1, "tid": 5, "ts": 44342980.46875, "dur": 1240.80002307892, "ph": "X", "name": "HashCompilerInvocation", "args": { "durationMS": 1.24080002307892, "detail": "UnityEngine.AudioModule_CodeGen.c" } },
{ "pid": 1, "tid": 5, "ts": 44344859.375, "dur": 17513.2999420166, "ph": "X", "name": "HashCompilerInvocation", "args": { "durationMS": 17.5132999420166, "detail": "inftrees.c" } },
{ "pid": 1, "tid": 5, "ts": 44363097.65625, "dur": 1059.80002880096, "ph": "X", "name": "HashCompilerInvocation", "args": { "durationMS": 1.05980002880096, "detail": "UnityEngine.InputLegacyModule_CodeGen.c" } },
{ "pid": 1, "tid": 5, "ts": 44364585.9375, "dur": 1373.49998950958, "ph": "X", "name": "HashCompilerInvocation", "args": { "durationMS": 1.37349998950958, "detail": "System.Configuration_CodeGen.c" } },
{ "pid": 1, "tid": 5, "ts": 44366441.40625, "dur": 2978.49988937378, "ph": "X", "name": "HashCompilerInvocation", "args": { "durationMS": 2.97849988937378, "detail": "adler32.c" } },
{ "pid": 1, "tid": 5, "ts": 44369910.15625, "dur": 897.700011730194, "ph": "X", "name": "HashCompilerInvocation", "args": { "durationMS": 0.897700011730194, "detail": "Il2CppReversePInvokeWrapperTable.cpp" } },
{ "pid": 1, "tid": 5, "ts": 44371304.6875, "dur": 1819.30005550385, "ph": "X", "name": "HashCompilerInvocation", "args": { "durationMS": 1.81930005550385, "detail": "compress.c" } },
{ "pid": 1, "tid": 5, "ts": 44373609.375, "dur": 693.400025367737, "ph": "X", "name": "HashCompilerInvocation", "args": { "durationMS": 0.693400025367737, "detail": "UnityEngine.UnityWebRequestModule_CodeGen.c" } },
{ "pid": 1, "tid": 5, "ts": 44374644.53125, "dur": 6195.00017166138, "ph": "X", "name": "HashCompilerInvocation", "args": { "durationMS": 6.19500017166138, "detail": "UnityAdsStubs.cpp" } },
{ "pid": 1, "tid": 5, "ts": 44381277.34375, "dur": 1192.80004501343, "ph": "X", "name": "HashCompilerInvocation", "args": { "durationMS": 1.19280004501343, "detail": "UnityEngine.cpp" } },
{ "pid": 1, "tid": 5, "ts": 44382843.75, "dur": 1112.69998550415, "ph": "X", "name": "HashCompilerInvocation", "args": { "durationMS": 1.11269998550415, "detail": "System.Xml_CodeGen.c" } },
{ "pid": 1, "tid": 5, "ts": 44384351.5625, "dur": 659.099996089935, "ph": "X", "name": "HashCompilerInvocation", "args": { "durationMS": 0.659099996089935, "detail": "Lump_libil2cpp_gc.cpp" } },
{ "pid": 1, "tid": 5, "ts": 44385875, "dur": 620.999991893768, "ph": "X", "name": "HashCompilerInvocation", "args": { "durationMS": 0.620999991893768, "detail": "System.Globalization.Extensions_CodeGen.c" } },
{ "pid": 1, "tid": 5, "ts": 44386859.375, "dur": 592.599987983704, "ph": "X", "name": "HashCompilerInvocation", "args": { "durationMS": 0.592599987983704, "detail": "netstandard_CodeGen.c" } },
{ "pid": 1, "tid": 5, "ts": 44388164.0625, "dur": 632.799983024597, "ph": "X", "name": "HashCompilerInvocation", "args": { "durationMS": 0.632799983024597, "detail": "Lump_libil2cpp_mono-runtime.cpp" } },
{ "pid": 1, "tid": 5, "ts": 44389128.90625, "dur": 615.700006484985, "ph": "X", "name": "HashCompilerInvocation", "args": { "durationMS": 0.615700006484985, "detail": "Il2CppGenericComDefinitions.cpp" } },
{ "pid": 1, "tid": 5, "ts": 44390121.09375, "dur": 1147.69995212555, "ph": "X", "name": "HashCompilerInvocation", "args": { "durationMS": 1.14769995212555, "detail": "il2cpp-runtime-stats.cpp" } },
{ "pid": 1, "tid": 6, "ph": "M", "name": "thread_name", "args": { "name": "" } },
{ "pid": 1, "tid": 6, "ts": 44023812.5, "dur": 85351.8981933594, "ph": "X", "name": "HashCompilerInvocation", "args": { "durationMS": 85.3518981933594, "detail": "Il2CppMetadataUsage.c" } },
{ "pid": 1, "tid": 6, "ts": 44109660.15625, "dur": 9259.90009307861, "ph": "X", "name": "HashCompilerInvocation", "args": { "durationMS": 9.25990009307861, "detail": "mscorlib9.cpp" } },
{ "pid": 1, "tid": 6, "ts": 44119351.5625, "dur": 10501.19972229, "ph": "X", "name": "HashCompilerInvocation", "args": { "durationMS": 10.50119972229, "detail": "mscorlib3.cpp" } },
{ "pid": 1, "tid": 6, "ts": 44130230.46875, "dur": 11990.9000396729, "ph": "X", "name": "HashCompilerInvocation", "args": { "durationMS": 11.9909000396729, "detail": "Cinemachine.cpp" } },
{ "pid": 1, "tid": 6, "ts": 44142652.34375, "dur": 9439.29958343506, "ph": "X", "name": "HashCompilerInvocation", "args": { "durationMS": 9.43929958343506, "detail": "mscorlib1.cpp" } },
{ "pid": 1, "tid": 6, "ts": 44152636.71875, "dur": 7856.59980773926, "ph": "X", "name": "HashCompilerInvocation", "args": { "durationMS": 7.85659980773926, "detail": "UnityEngine.CoreModule.cpp" } },
{ "pid": 1, "tid": 6, "ts": 44160929.6875, "dur": 8473.50025177002, "ph": "X", "name": "HashCompilerInvocation", "args": { "durationMS": 8.47350025177002, "detail": "Generics.cpp" } },
{ "pid": 1, "tid": 6, "ts": 44170007.8125, "dur": 8458.70018005371, "ph": "X", "name": "HashCompilerInvocation", "args": { "durationMS": 8.45870018005371, "detail": "Generics6.cpp" } },
{ "pid": 1, "tid": 6, "ts": 44178972.65625, "dur": 8074.00035858154, "ph": "X", "name": "HashCompilerInvocation", "args": { "durationMS": 8.07400035858154, "detail": "mscorlib5.cpp" } },
{ "pid": 1, "tid": 6, "ts": 44187582.03125, "dur": 7023.60010147095, "ph": "X", "name": "HashCompilerInvocation", "args": { "durationMS": 7.02360010147095, "detail": "Generics13.cpp" } },
{ "pid": 1, "tid": 6, "ts": 44195039.0625, "dur": 8069.60010528564, "ph": "X", "name": "HashCompilerInvocation", "args": { "durationMS": 8.06960010528564, "detail": "mscorlib14.cpp" } },
{ "pid": 1, "tid": 6, "ts": 44203539.0625, "dur": 7027.40001678467, "ph": "X", "name": "HashCompilerInvocation", "args": { "durationMS": 7.02740001678467, "detail": "Generics14.cpp" } },
{ "pid": 1, "tid": 6, "ts": 44211058.59375, "dur": 5765.79999923706, "ph": "X", "name": "HashCompilerInvocation", "args": { "durationMS": 5.76579999923706, "detail": "Generics5.cpp" } },
{ "pid": 1, "tid": 6, "ts": 44217265.625, "dur": 6354.59995269775, "ph": "X", "name": "HashCompilerInvocation", "args": { "durationMS": 6.35459995269775, "detail": "Generics7.cpp" } },
{ "pid": 1, "tid": 6, "ts": 44224125, "dur": 5668.70021820068, "ph": "X", "name": "HashCompilerInvocation", "args": { "durationMS": 5.66870021820068, "detail": "Generics11.cpp" } },
{ "pid": 1, "tid": 6, "ts": 44230230.46875, "dur": 3755.50007820129, "ph": "X", "name": "HashCompilerInvocation", "args": { "durationMS": 3.75550007820129, "detail": "Il2CppGenericInstDefinitions.c" } },
{ "pid": 1, "tid": 6, "ts": 44234914.0625, "dur": 23578.8993835449, "ph": "X", "name": "HashCompilerInvocation", "args": { "durationMS": 23.5788993835449, "detail": "char-conversions.cpp" } },
{ "pid": 1, "tid": 6, "ts": 44259066.40625, "dur": 1106.09996318817, "ph": "X", "name": "HashCompilerInvocation", "args": { "durationMS": 1.10609996318817, "detail": "UnityEngine.IMGUIModule_CodeGen.c" } },
{ "pid": 1, "tid": 6, "ts": 44260605.46875, "dur": 20373.1994628906, "ph": "X", "name": "HashCompilerInvocation", "args": { "durationMS": 20.3731994628906, "detail": "inflate.c" } },
{ "pid": 1, "tid": 6, "ts": 44281304.6875, "dur": 610.599994659424, "ph": "X", "name": "HashCompilerInvocation", "args": { "durationMS": 0.610599994659424, "detail": "UnityEngine.PhysicsModule_CodeGen.c" } },
{ "pid": 1, "tid": 6, "ts": 44282687.5, "dur": 731.99999332428, "ph": "X", "name": "HashCompilerInvocation", "args": { "durationMS": 0.73199999332428, "detail": "UnityEngine.UIModule_CodeGen.c" } },
{ "pid": 1, "tid": 6, "ts": 44283730.46875, "dur": 51951.8013000488, "ph": "X", "name": "HashCompilerInvocation", "args": { "durationMS": 51.9518013000488, "detail": "infback.c" } },
{ "pid": 1, "tid": 6, "ts": 44336164.0625, "dur": 26077.9991149902, "ph": "X", "name": "HashCompilerInvocation", "args": { "durationMS": 26.0779991149902, "detail": "gzlib.c" } },
{ "pid": 1, "tid": 6, "ts": 44363046.875, "dur": 909.600019454956, "ph": "X", "name": "HashCompilerInvocation", "args": { "durationMS": 0.909600019454956, "detail": "Assembly-CSharp_CodeGen.c" } },
{ "pid": 1, "tid": 6, "ts": 44364523.4375, "dur": 19820.7015991211, "ph": "X", "name": "HashCompilerInvocation", "args": { "durationMS": 19.8207015991211, "detail": "zutil.c" } },
{ "pid": 1, "tid": 6, "ts": 44384851.5625, "dur": 24881.3991546631, "ph": "X", "name": "HashCompilerInvocation", "args": { "durationMS": 24.8813991546631, "detail": "il2cpp-benchmark-support.cpp" } },
{ "pid": 1, "tid": 4, "ph": "M", "name": "thread_name", "args": { "name": "" } },
{ "pid": 1, "tid": 4, "ts": 44023898.4375, "dur": 102148.406982422, "ph": "X", "name": "HashCompilerInvocation", "args": { "durationMS": 102.148406982422, "detail": "Il2CppTypeDefinitions.c" } },
{ "pid": 1, "tid": 4, "ts": 44126617.1875, "dur": 9381.29997253418, "ph": "X", "name": "HashCompilerInvocation", "args": { "durationMS": 9.38129997253418, "detail": "UnityEngine.UI.cpp" } },
{ "pid": 1, "tid": 4, "ts": 44136546.875, "dur": 9134.40036773682, "ph": "X", "name": "HashCompilerInvocation", "args": { "durationMS": 9.13440036773682, "detail": "mscorlib7.cpp" } },
{ "pid": 1, "tid": 4, "ts": 44146132.8125, "dur": 9012.29953765869, "ph": "X", "name": "HashCompilerInvocation", "args": { "durationMS": 9.01229953765869, "detail": "mscorlib6.cpp" } },
{ "pid": 1, "tid": 4, "ts": 44155589.84375, "dur": 10171.6003417969, "ph": "X", "name": "HashCompilerInvocation", "args": { "durationMS": 10.1716003417969, "detail": "mscorlib10.cpp" } },
{ "pid": 1, "tid": 4, "ts": 44166281.25, "dur": 8684.59987640381, "ph": "X", "name": "HashCompilerInvocation", "args": { "durationMS": 8.68459987640381, "detail": "Generics1.cpp" } },
{ "pid": 1, "tid": 4, "ts": 44175445.3125, "dur": 7057.40022659302, "ph": "X", "name": "HashCompilerInvocation", "args": { "durationMS": 7.05740022659302, "detail": "Il2CppCompilerCalculateTypeValues1.cpp" } },
{ "pid": 1, "tid": 4, "ts": 44182953.125, "dur": 7947.40009307861, "ph": "X", "name": "HashCompilerInvocation", "args": { "durationMS": 7.94740009307861, "detail": "mscorlib2.cpp" } },
{ "pid": 1, "tid": 4, "ts": 44191332.03125, "dur": 8367.79975891113, "ph": "X", "name": "HashCompilerInvocation", "args": { "durationMS": 8.36779975891113, "detail": "Generics10.cpp" } },
{ "pid": 1, "tid": 4, "ts": 44200136.71875, "dur": 6373.09980392456, "ph": "X", "name": "HashCompilerInvocation", "args": { "durationMS": 6.37309980392456, "detail": "Generics3.cpp" } },
{ "pid": 1, "tid": 4, "ts": 44207035.15625, "dur": 6903.39994430542, "ph": "X", "name": "HashCompilerInvocation", "args": { "durationMS": 6.90339994430542, "detail": "Generics9.cpp" } },
{ "pid": 1, "tid": 4, "ts": 44214375, "dur": 6245.1000213623, "ph": "X", "name": "HashCompilerInvocation", "args": { "durationMS": 6.2451000213623, "detail": "GenericMethods4.cpp" } },
{ "pid": 1, "tid": 4, "ts": 44221105.46875, "dur": 5571.70009613037, "ph": "X", "name": "HashCompilerInvocation", "args": { "durationMS": 5.57170009613037, "detail": "Generics2.cpp" } },
{ "pid": 1, "tid": 4, "ts": 44227167.96875, "dur": 5527.10008621216, "ph": "X", "name": "HashCompilerInvocation", "args": { "durationMS": 5.52710008621216, "detail": "Il2CppGenericClassTable.c" } },
{ "pid": 1, "tid": 4, "ts": 44233128.90625, "dur": 2840.60001373291, "ph": "X", "name": "HashCompilerInvocation", "args": { "durationMS": 2.84060001373291, "detail": "UnityEngine.AnimationModule.cpp" } },
{ "pid": 1, "tid": 4, "ts": 44236382.8125, "dur": 2261.3000869751, "ph": "X", "name": "HashCompilerInvocation", "args": { "durationMS": 2.2613000869751, "detail": "UnresolvedVirtualCallStubs.cpp" } },
{ "pid": 1, "tid": 4, "ts": 44239070.3125, "dur": 2461.60006523132, "ph": "X", "name": "HashCompilerInvocation", "args": { "durationMS": 2.46160006523132, "detail": "Assembly-CSharp.cpp" } },
{ "pid": 1, "tid": 4, "ts": 44241949.21875, "dur": 1818.50004196167, "ph": "X", "name": "HashCompilerInvocation", "args": { "durationMS": 1.81850004196167, "detail": "UnityEngine.PhysicsModule.cpp" } },
{ "pid": 1, "tid": 4, "ts": 44244191.40625, "dur": 1265.20001888275, "ph": "X", "name": "HashCompilerInvocation", "args": { "durationMS": 1.26520001888275, "detail": "UnityEngine.SharedInternalsModule.cpp" } },
{ "pid": 1, "tid": 4, "ts": 44245867.1875, "dur": 1878.70001792908, "ph": "X", "name": "HashCompilerInvocation", "args": { "durationMS": 1.87870001792908, "detail": "Il2CppInteropDataTable.cpp" } },
{ "pid": 1, "tid": 4, "ts": 44248152.34375, "dur": 1170.79997062683, "ph": "X", "name": "HashCompilerInvocation", "args": { "durationMS": 1.17079997062683, "detail": "UnityEngine.AudioModule.cpp" } },
{ "pid": 1, "tid": 4, "ts": 44249765.625, "dur": 8707.90004730225, "ph": "X", "name": "HashCompilerInvocation", "args": { "durationMS": 8.70790004730225, "detail": "UnityEngine.UnityWebRequestModule.cpp" } },
{ "pid": 1, "tid": 4, "ts": 44259066.40625, "dur": 1127.40004062653, "ph": "X", "name": "HashCompilerInvocation", "args": { "durationMS": 1.12740004062653, "detail": "UnityEngine.AnimationModule_CodeGen.c" } },
{ "pid": 1, "tid": 4, "ts": 44260558.59375, "dur": 65319.0002441406, "ph": "X", "name": "HashCompilerInvocation", "args": { "durationMS": 65.3190002441406, "detail": "trees.c" } },
{ "pid": 1, "tid": 4, "ts": 44326550.78125, "dur": 2363.80004882813, "ph": "X", "name": "HashCompilerInvocation", "args": { "durationMS": 2.36380004882813, "detail": "Lump_libil2cpp_os.cpp" } },
{ "pid": 1, "tid": 4, "ts": 44330144.53125, "dur": 1146.99995517731, "ph": "X", "name": "HashCompilerInvocation", "args": { "durationMS": 1.14699995517731, "detail": "Lump_libil2cpp_icalls.cpp" } },
{ "pid": 1, "tid": 4, "ts": 44331804.6875, "dur": 1377.20000743866, "ph": "X", "name": "HashCompilerInvocation", "args": { "durationMS": 1.37720000743866, "detail": "UnityEngine.Physics2DModule_CodeGen.c" } },
{ "pid": 1, "tid": 4, "ts": 44333546.875, "dur": 28563.0016326904, "ph": "X", "name": "HashCompilerInvocation", "args": { "durationMS": 28.5630016326904, "detail": "gzwrite.c" } },
{ "pid": 1, "tid": 4, "ts": 44363011.71875, "dur": 2684.60011482239, "ph": "X", "name": "HashCompilerInvocation", "args": { "durationMS": 2.68460011482239, "detail": "inffast.c" } },
{ "pid": 1, "tid": 4, "ts": 44366238.28125, "dur": 1436.30003929138, "ph": "X", "name": "HashCompilerInvocation", "args": { "durationMS": 1.43630003929138, "detail": "UnityEngine.UnityAnalyticsModule_CodeGen.c" } },
{ "pid": 1, "tid": 4, "ts": 44368085.9375, "dur": 771.600008010864, "ph": "X", "name": "HashCompilerInvocation", "args": { "durationMS": 0.771600008010864, "detail": "Il2CppCodeRegistration.cpp" } },
{ "pid": 1, "tid": 4, "ts": 44369441.40625, "dur": 872.099995613098, "ph": "X", "name": "HashCompilerInvocation", "args": { "durationMS": 0.872099995613098, "detail": "Mono.Security_CodeGen.c" } },
{ "pid": 1, "tid": 4, "ts": 44370839.84375, "dur": 20466.1998748779, "ph": "X", "name": "HashCompilerInvocation", "args": { "durationMS": 20.4661998748779, "detail": "uncompr.c" } },
{ "pid": 1, "tid": 11, "ph": "M", "name": "thread_name", "args": { "name": "" } },
{ "pid": 1, "tid": 11, "ts": 44420804.6875, "dur": 10659066.40625, "ph": "X", "name": "Compile", "args": { "durationMS": 10659.06640625, "detail": "Il2CppCompilerCalculateTypeValues1.cpp" } },
{ "pid": 1, "tid": 11, "ts": 55079882.8125, "dur": 2104988.76953125, "ph": "X", "name": "Compile", "args": { "durationMS": 2104.98876953125, "detail": "UnityEngine.CoreModule_CodeGen.c" } },
{ "pid": 1, "tid": 11, "ts": 57184898.4375, "dur": 4116194.3359375, "ph": "X", "name": "Compile", "args": { "durationMS": 4116.1943359375, "detail": "Il2CppCompilerCalculateTypeValuesTable.cpp" } },
{ "pid": 1, "tid": 11, "ts": 61301101.5625, "dur": 2322754.8828125, "ph": "X", "name": "Compile", "args": { "durationMS": 2322.7548828125, "detail": "Assembly-CSharp_CodeGen.c" } },
{ "pid": 1, "tid": 8, "ph": "M", "name": "thread_name", "args": { "name": "" } },
{ "pid": 1, "tid": 8, "ts": 44420812.5, "dur": 10521005.859375, "ph": "X", "name": "Compile", "args": { "durationMS": 10521.005859375, "detail": "Il2CppMetadataUsage.c" } },
{ "pid": 1, "tid": 8, "ts": 54942238.28125, "dur": 2368091.06445313, "ph": "X", "name": "Compile", "args": { "durationMS": 2368.09106445313, "detail": "Il2CppGenericMethodDefinitions.c" } },
{ "pid": 1, "tid": 8, "ts": 57310339.84375, "dur": 4278346.6796875, "ph": "X", "name": "Compile", "args": { "durationMS": 4278.3466796875, "detail": "Assembly-CSharp.cpp" } },
{ "pid": 1, "tid": 8, "ts": 61588703.125, "dur": 2138768.31054688, "ph": "X", "name": "Compile", "args": { "durationMS": 2138.76831054688, "detail": "Il2CppMetadataRegistration.c" } },
{ "pid": 1, "tid": 9, "ph": "M", "name": "thread_name", "args": { "name": "" } },
{ "pid": 1, "tid": 9, "ts": 44420851.5625, "dur": 17037792.96875, "ph": "X", "name": "Compile", "args": { "durationMS": 17037.79296875, "detail": "Il2CppAttributes.cpp" } },
{ "pid": 1, "tid": 9, "ts": 61458664.0625, "dur": 2380916.74804688, "ph": "X", "name": "Compile", "args": { "durationMS": 2380.91674804688, "detail": "Il2CppCodeRegistration.cpp" } },
{ "pid": 1, "tid": 10, "ph": "M", "name": "thread_name", "args": { "name": "" } },
{ "pid": 1, "tid": 10, "ts": 44420894.53125, "dur": 14676161.1328125, "ph": "X", "name": "Compile", "args": { "durationMS": 14676.1611328125, "detail": "UnityEngine.CoreModule.cpp" } },
{ "pid": 1, "tid": 10, "ts": 59097074.21875, "dur": 3254950.68359375, "ph": "X", "name": "Compile", "args": { "durationMS": 3254.95068359375, "detail": "UnityICallRegistration.cpp" } }
],
"meta_datetime": "01/10/2020 10:20:28",
"meta_command_line": "\"C:\\Program Files\\Unity\\Hub\\Editor\\2019.2.16f1\\Editor\\Data\\il2cpp/build/il2cpp.exe\" --convert-to-cpp --dotnetprofile=\"unityaot\" --compile-cpp --libil2cpp-static --platform=\"WebGL\" --architecture=\"EmscriptenJavaScript\" --configuration=\"Release\" --outputpath=\"C:\\Users\\Marti\\Documents\\GitHub\\RPG-201920\\rpg_201920\\Assets /../Temp/StagingArea/Data\\Native\\build.bc\" --cachedirectory=\"C:\\Users\\Marti\\Documents\\GitHub\\RPG-201920\\rpg_201920\\Assets\\..\\Library/il2cpp_cache\" --compiler-flags=\"-Oz -DIL2CPP_EXCEPTION_DISABLED=1 \" --emit-method-map --additional-libraries=\"C:/Program Files/Unity/Hub/Editor/2019.2.16f1/Editor/Data/PlaybackEngines/WebGLSupport\\BuildTools\\lib\\modules\\WebGLSupport_AccessibilityModule_Dynamic.bc\" --additional-libraries=\"C:/Program Files/Unity/Hub/Editor/2019.2.16f1/Editor/Data/PlaybackEngines/WebGLSupport\\BuildTools\\lib\\modules\\WebGLSupport_AIModule_Dynamic.bc\" --additional-libraries=\"C:/Program Files/Unity/Hub/Editor/2019.2.16f1/Editor/Data/PlaybackEngines/WebGLSupport\\BuildTools\\lib\\modules\\WebGLSupport_AndroidJNIModule_Dynamic.bc\" --additional-libraries=\"C:/Program Files/Unity/Hub/Editor/2019.2.16f1/Editor/Data/PlaybackEngines/WebGLSupport\\BuildTools\\lib\\modules\\WebGLSupport_AnimationModule_Dynamic.bc\" --additional-libraries=\"C:/Program Files/Unity/Hub/Editor/2019.2.16f1/Editor/Data/PlaybackEngines/WebGLSupport\\BuildTools\\lib\\modules\\WebGLSupport_ARModule_Dynamic.bc\" --additional-libraries=\"C:/Program Files/Unity/Hub/Editor/2019.2.16f1/Editor/Data/PlaybackEngines/WebGLSupport\\BuildTools\\lib\\modules\\WebGLSupport_AssetBundleModule_Dynamic.bc\" --additional-libraries=\"C:/Program Files/Unity/Hub/Editor/2019.2.16f1/Editor/Data/PlaybackEngines/WebGLSupport\\BuildTools\\lib\\modules\\WebGLSupport_AudioModule_Dynamic.bc\" --additional-libraries=\"C:/Program Files/Unity/Hub/Editor/2019.2.16f1/Editor/Data/PlaybackEngines/WebGLSupport\\BuildTools\\lib\\modules\\WebGLSupport_ClothModule_Dynamic.bc\" --additional-libraries=\"C:/Program Files/Unity/Hub/Editor/2019.2.16f1/Editor/Data/PlaybackEngines/WebGLSupport\\BuildTools\\lib\\modules\\WebGLSupport_CoreModule_Dynamic.bc\" --additional-libraries=\"C:/Program Files/Unity/Hub/Editor/2019.2.16f1/Editor/Data/PlaybackEngines/WebGLSupport\\BuildTools\\lib\\modules\\WebGLSupport_CrashReportingModule_Dynamic.bc\" --additional-libraries=\"C:/Program Files/Unity/Hub/Editor/2019.2.16f1/Editor/Data/PlaybackEngines/WebGLSupport\\BuildTools\\lib\\modules\\WebGLSupport_DirectorModule_Dynamic.bc\" --additional-libraries=\"C:/Program Files/Unity/Hub/Editor/2019.2.16f1/Editor/Data/PlaybackEngines/WebGLSupport\\BuildTools\\lib\\modules\\WebGLSupport_DSPGraphModule_Dynamic.bc\" --additional-libraries=\"C:/Program Files/Unity/Hub/Editor/2019.2.16f1/Editor/Data/PlaybackEngines/WebGLSupport\\BuildTools\\lib\\modules\\WebGLSupport_FileSystemHttpModule_Dynamic.bc\" --additional-libraries=\"C:/Program Files/Unity/Hub/Editor/2019.2.16f1/Editor/Data/PlaybackEngines/WebGLSupport\\BuildTools\\lib\\modules\\WebGLSupport_GameCenterModule_Dynamic.bc\" --additional-libraries=\"C:/Program Files/Unity/Hub/Editor/2019.2.16f1/Editor/Data/PlaybackEngines/WebGLSupport\\BuildTools\\lib\\modules\\WebGLSupport_GridModule_Dynamic.bc\" --additional-libraries=\"C:/Program Files/Unity/Hub/Editor/2019.2.16f1/Editor/Data/PlaybackEngines/WebGLSupport\\BuildTools\\lib\\modules\\WebGLSupport_HotReloadModule_Dynamic.bc\" --additional-libraries=\"C:/Program Files/Unity/Hub/Editor/2019.2.16f1/Editor/Data/PlaybackEngines/WebGLSupport\\BuildTools\\lib\\modules\\WebGLSupport_ImageConversionModule_Dynamic.bc\" --additional-libraries=\"C:/Program Files/Unity/Hub/Editor/2019.2.16f1/Editor/Data/PlaybackEngines/WebGLSupport\\BuildTools\\lib\\modules\\WebGLSupport_IMGUIModule_Dynamic.bc\" --additional-libraries=\"C:/Program Files/Unity/Hub/Editor/2019.2.16f1/Editor/Data/PlaybackEngines/WebGLSupport\\BuildTools\\lib\\modules\\WebGLSupport_InputLegacyModule_Dynamic.bc\" --additional-libraries=\"C:/Program Files/Unity/Hub/Editor/2019.2.16f1/Editor/Data/PlaybackEngines/WebGLSupport\\BuildTools\\lib\\modules\\WebGLSupport_InputModule_Dynamic.bc\" --additional-libraries=\"C:/Program Files/Unity/Hub/Editor/2019.2.16f1/Editor/Data/PlaybackEngines/WebGLSupport\\BuildTools\\lib\\modules\\WebGLSupport_JSONSerializeModule_Dynamic.bc\" --additional-libraries=\"C:/Program Files/Unity/Hub/Editor/2019.2.16f1/Editor/Data/PlaybackEngines/WebGLSupport\\BuildTools\\lib\\modules\\WebGLSupport_LocalizationModule_Dynamic.bc\" --additional-libraries=\"C:/Program Files/Unity/Hub/Editor/2019.2.16f1/Editor/Data/PlaybackEngines/WebGLSupport\\BuildTools\\lib\\modules\\WebGLSupport_ParticleSystemModule_Dynamic.bc\" --additional-libraries=\"C:/Program Files/Unity/Hub/Editor/2019.2.16f1/Editor/Data/PlaybackEngines/WebGLSupport\\BuildTools\\lib\\modules\\WebGLSupport_PerformanceReportingModule_Dynamic.bc\" --additional-libraries=\"C:/Program Files/Unity/Hub/Editor/2019.2.16f1/Editor/Data/PlaybackEngines/WebGLSupport\\BuildTools\\lib\\modules\\WebGLSupport_Physics2DModule_Dynamic.bc\" --additional-libraries=\"C:/Program Files/Unity/Hub/Editor/2019.2.16f1/Editor/Data/PlaybackEngines/WebGLSupport\\BuildTools\\lib\\modules\\WebGLSupport_PhysicsModule_Dynamic.bc\" --additional-libraries=\"C:/Program Files/Unity/Hub/Editor/2019.2.16f1/Editor/Data/PlaybackEngines/WebGLSupport\\BuildTools\\lib\\modules\\WebGLSupport_ProfilerModule_Dynamic.bc\" --additional-libraries=\"C:/Program Files/Unity/Hub/Editor/2019.2.16f1/Editor/Data/PlaybackEngines/WebGLSupport\\BuildTools\\lib\\modules\\WebGLSupport_ScreenCaptureModule_Dynamic.bc\" --additional-libraries=\"C:/Program Files/Unity/Hub/Editor/2019.2.16f1/Editor/Data/PlaybackEngines/WebGLSupport\\BuildTools\\lib\\modules\\WebGLSupport_SharedInternalsModule_Dynamic.bc\" --additional-libraries=\"C:/Program Files/Unity/Hub/Editor/2019.2.16f1/Editor/Data/PlaybackEngines/WebGLSupport\\BuildTools\\lib\\modules\\WebGLSupport_SpriteMaskModule_Dynamic.bc\" --additional-libraries=\"C:/Program Files/Unity/Hub/Editor/2019.2.16f1/Editor/Data/PlaybackEngines/WebGLSupport\\BuildTools\\lib\\modules\\WebGLSupport_SpriteShapeModule_Dynamic.bc\" --additional-libraries=\"C:/Program Files/Unity/Hub/Editor/2019.2.16f1/Editor/Data/PlaybackEngines/WebGLSupport\\BuildTools\\lib\\modules\\WebGLSupport_StreamingModule_Dynamic.bc\" --additional-libraries=\"C:/Program Files/Unity/Hub/Editor/2019.2.16f1/Editor/Data/PlaybackEngines/WebGLSupport\\BuildTools\\lib\\modules\\WebGLSupport_SubstanceModule_Dynamic.bc\" --additional-libraries=\"C:/Program Files/Unity/Hub/Editor/2019.2.16f1/Editor/Data/PlaybackEngines/WebGLSupport\\BuildTools\\lib\\modules\\WebGLSupport_TerrainModule_Dynamic.bc\" --additional-libraries=\"C:/Program Files/Unity/Hub/Editor/2019.2.16f1/Editor/Data/PlaybackEngines/WebGLSupport\\BuildTools\\lib\\modules\\WebGLSupport_TerrainPhysicsModule_Dynamic.bc\" --additional-libraries=\"C:/Program Files/Unity/Hub/Editor/2019.2.16f1/Editor/Data/PlaybackEngines/WebGLSupport\\BuildTools\\lib\\modules\\WebGLSupport_TextCoreModule_Dynamic.bc\" --additional-libraries=\"C:/Program Files/Unity/Hub/Editor/2019.2.16f1/Editor/Data/PlaybackEngines/WebGLSupport\\BuildTools\\lib\\modules\\WebGLSupport_TextRenderingModule_Dynamic.bc\" --additional-libraries=\"C:/Program Files/Unity/Hub/Editor/2019.2.16f1/Editor/Data/PlaybackEngines/WebGLSupport\\BuildTools\\lib\\modules\\WebGLSupport_TilemapModule_Dynamic.bc\" --additional-libraries=\"C:/Program Files/Unity/Hub/Editor/2019.2.16f1/Editor/Data/PlaybackEngines/WebGLSupport\\BuildTools\\lib\\modules\\WebGLSupport_TLSModule_Dynamic.bc\" --additional-libraries=\"C:/Program Files/Unity/Hub/Editor/2019.2.16f1/Editor/Data/PlaybackEngines/WebGLSupport\\BuildTools\\lib\\modules\\WebGLSupport_UIElementsModule_Dynamic.bc\" --additional-libraries=\"C:/Program Files/Unity/Hub/Editor/2019.2.16f1/Editor/Data/PlaybackEngines/WebGLSupport\\BuildTools\\lib\\modules\\WebGLSupport_UIModule_Dynamic.bc\" --additional-libraries=\"C:/Program Files/Unity/Hub/Editor/2019.2.16f1/Editor/Data/PlaybackEngines/WebGLSupport\\BuildTools\\lib\\modules\\WebGLSupport_UmbraModule_Dynamic.bc\" --additional-libraries=\"C:/Program Files/Unity/Hub/Editor/2019.2.16f1/Editor/Data/PlaybackEngines/WebGLSupport\\BuildTools\\lib\\modules\\WebGLSupport_UNETModule_Dynamic.bc\" --additional-libraries=\"C:/Program Files/Unity/Hub/Editor/2019.2.16f1/Editor/Data/PlaybackEngines/WebGLSupport\\BuildTools\\lib\\modules\\WebGLSupport_UnityAnalyticsModule_Dynamic.bc\" --additional-libraries=\"C:/Program Files/Unity/Hub/Editor/2019.2.16f1/Editor/Data/PlaybackEngines/WebGLSupport\\BuildTools\\lib\\modules\\WebGLSupport_UnityConnectModule_Dynamic.bc\" --additional-libraries=\"C:/Program Files/Unity/Hub/Editor/2019.2.16f1/Editor/Data/PlaybackEngines/WebGLSupport\\BuildTools\\lib\\modules\\WebGLSupport_UnityTestProtocolModule_Dynamic.bc\" --additional-libraries=\"C:/Program Files/Unity/Hub/Editor/2019.2.16f1/Editor/Data/PlaybackEngines/WebGLSupport\\BuildTools\\lib\\modules\\WebGLSupport_UnityWebRequestAssetBundleModule_Dynamic.bc\" --additional-libraries=\"C:/Program Files/Unity/Hub/Editor/2019.2.16f1/Editor/Data/PlaybackEngines/WebGLSupport\\BuildTools\\lib\\modules\\WebGLSupport_UnityWebRequestAudioModule_Dynamic.bc\" --additional-libraries=\"C:/Program Files/Unity/Hub/Editor/2019.2.16f1/Editor/Data/PlaybackEngines/WebGLSupport\\BuildTools\\lib\\modules\\WebGLSupport_UnityWebRequestModule_Dynamic.bc\" --additional-libraries=\"C:/Program Files/Unity/Hub/Editor/2019.2.16f1/Editor/Data/PlaybackEngines/WebGLSupport\\BuildTools\\lib\\modules\\WebGLSupport_UnityWebRequestTextureModule_Dynamic.bc\" --additional-libraries=\"C:/Program Files/Unity/Hub/Editor/2019.2.16f1/Editor/Data/PlaybackEngines/WebGLSupport\\BuildTools\\lib\\modules\\WebGLSupport_UnityWebRequestWWWModule_Dynamic.bc\" --additional-libraries=\"C:/Program Files/Unity/Hub/Editor/2019.2.16f1/Editor/Data/PlaybackEngines/WebGLSupport\\BuildTools\\lib\\modules\\WebGLSupport_VehiclesModule_Dynamic.bc\" --additional-libraries=\"C:/Program Files/Unity/Hub/Editor/2019.2.16f1/Editor/Data/PlaybackEngines/WebGLSupport\\BuildTools\\lib\\modules\\WebGLSupport_VFXModule_Dynamic.bc\" --additional-libraries=\"C:/Program Files/Unity/Hub/Editor/2019.2.16f1/Editor/Data/PlaybackEngines/WebGLSupport\\BuildTools\\lib\\modules\\WebGLSupport_VideoModule_Dynamic.bc\" --additional-libraries=\"C:/Program Files/Unity/Hub/Editor/2019.2.16f1/Editor/Data/PlaybackEngines/WebGLSupport\\BuildTools\\lib\\modules\\WebGLSupport_VRModule_Dynamic.bc\" --additional-libraries=\"C:/Program Files/Unity/Hub/Editor/2019.2.16f1/Editor/Data/PlaybackEngines/WebGLSupport\\BuildTools\\lib\\modules\\WebGLSupport_WebGLModule_Dynamic.bc\" --additional-libraries=\"C:/Program Files/Unity/Hub/Editor/2019.2.16f1/Editor/Data/PlaybackEngines/WebGLSupport\\BuildTools\\lib\\modules\\WebGLSupport_WindModule_Dynamic.bc\" --additional-libraries=\"C:/Program Files/Unity/Hub/Editor/2019.2.16f1/Editor/Data/PlaybackEngines/WebGLSupport\\BuildTools\\lib\\modules\\WebGLSupport_XRModule_Dynamic.bc\" --profiler-report --map-file-parser=\"C:/Program Files/Unity/Hub/Editor/2019.2.16f1/Editor/Data/Tools/MapFileParser/MapFileParser.exe\" --directory=C:/Users/Marti/Documents/GitHub/RPG-201920/rpg_201920/Temp/StagingArea/Data/Managed --generatedcppdir=C:/Users/Marti/Documents/GitHub/RPG-201920/rpg_201920/Temp/StagingArea/Data/il2cppOutput ",
"meta_command_line_args": "C:\\Program Files\\Unity\\Hub\\Editor\\2019.2.16f1\\Editor\\Data\\il2cpp/build/il2cpp.exe --convert-to-cpp --dotnetprofile=unityaot --compile-cpp --libil2cpp-static --platform=WebGL --architecture=EmscriptenJavaScript --configuration=Release --outputpath=C:\\Users\\Marti\\Documents\\GitHub\\RPG-201920\\rpg_201920\\Assets /../Temp/StagingArea/Data\\Native\\build.bc --cachedirectory=C:\\Users\\Marti\\Documents\\GitHub\\RPG-201920\\rpg_201920\\Assets\\..\\Library/il2cpp_cache --compiler-flags=-Oz -DIL2CPP_EXCEPTION_DISABLED=1  --emit-method-map --additional-libraries=C:/Program Files/Unity/Hub/Editor/2019.2.16f1/Editor/Data/PlaybackEngines/WebGLSupport\\BuildTools\\lib\\modules\\WebGLSupport_AccessibilityModule_Dynamic.bc --additional-libraries=C:/Program Files/Unity/Hub/Editor/2019.2.16f1/Editor/Data/PlaybackEngines/WebGLSupport\\BuildTools\\lib\\modules\\WebGLSupport_AIModule_Dynamic.bc --additional-libraries=C:/Program Files/Unity/Hub/Editor/2019.2.16f1/Editor/Data/PlaybackEngines/WebGLSupport\\BuildTools\\lib\\modules\\WebGLSupport_AndroidJNIModule_Dynamic.bc --additional-libraries=C:/Program Files/Unity/Hub/Editor/2019.2.16f1/Editor/Data/PlaybackEngines/WebGLSupport\\BuildTools\\lib\\modules\\WebGLSupport_AnimationModule_Dynamic.bc --additional-libraries=C:/Program Files/Unity/Hub/Editor/2019.2.16f1/Editor/Data/PlaybackEngines/WebGLSupport\\BuildTools\\lib\\modules\\WebGLSupport_ARModule_Dynamic.bc --additional-libraries=C:/Program Files/Unity/Hub/Editor/2019.2.16f1/Editor/Data/PlaybackEngines/WebGLSupport\\BuildTools\\lib\\modules\\WebGLSupport_AssetBundleModule_Dynamic.bc --additional-libraries=C:/Program Files/Unity/Hub/Editor/2019.2.16f1/Editor/Data/PlaybackEngines/WebGLSupport\\BuildTools\\lib\\modules\\WebGLSupport_AudioModule_Dynamic.bc --additional-libraries=C:/Program Files/Unity/Hub/Editor/2019.2.16f1/Editor/Data/PlaybackEngines/WebGLSupport\\BuildTools\\lib\\modules\\WebGLSupport_ClothModule_Dynamic.bc --additional-libraries=C:/Program Files/Unity/Hub/Editor/2019.2.16f1/Editor/Data/PlaybackEngines/WebGLSupport\\BuildTools\\lib\\modules\\WebGLSupport_CoreModule_Dynamic.bc --additional-libraries=C:/Program Files/Unity/Hub/Editor/2019.2.16f1/Editor/Data/PlaybackEngines/WebGLSupport\\BuildTools\\lib\\modules\\WebGLSupport_CrashReportingModule_Dynamic.bc --additional-libraries=C:/Program Files/Unity/Hub/Editor/2019.2.16f1/Editor/Data/PlaybackEngines/WebGLSupport\\BuildTools\\lib\\modules\\WebGLSupport_DirectorModule_Dynamic.bc --additional-libraries=C:/Program Files/Unity/Hub/Editor/2019.2.16f1/Editor/Data/PlaybackEngines/WebGLSupport\\BuildTools\\lib\\modules\\WebGLSupport_DSPGraphModule_Dynamic.bc --additional-libraries=C:/Program Files/Unity/Hub/Editor/2019.2.16f1/Editor/Data/PlaybackEngines/WebGLSupport\\BuildTools\\lib\\modules\\WebGLSupport_FileSystemHttpModule_Dynamic.bc --additional-libraries=C:/Program Files/Unity/Hub/Editor/2019.2.16f1/Editor/Data/PlaybackEngines/WebGLSupport\\BuildTools\\lib\\modules\\WebGLSupport_GameCenterModule_Dynamic.bc --additional-libraries=C:/Program Files/Unity/Hub/Editor/2019.2.16f1/Editor/Data/PlaybackEngines/WebGLSupport\\BuildTools\\lib\\modules\\WebGLSupport_GridModule_Dynamic.bc --additional-libraries=C:/Program Files/Unity/Hub/Editor/2019.2.16f1/Editor/Data/PlaybackEngines/WebGLSupport\\BuildTools\\lib\\modules\\WebGLSupport_HotReloadModule_Dynamic.bc --additional-libraries=C:/Program Files/Unity/Hub/Editor/2019.2.16f1/Editor/Data/PlaybackEngines/WebGLSupport\\BuildTools\\lib\\modules\\WebGLSupport_ImageConversionModule_Dynamic.bc --additional-libraries=C:/Program Files/Unity/Hub/Editor/2019.2.16f1/Editor/Data/PlaybackEngines/WebGLSupport\\BuildTools\\lib\\modules\\WebGLSupport_IMGUIModule_Dynamic.bc --additional-libraries=C:/Program Files/Unity/Hub/Editor/2019.2.16f1/Editor/Data/PlaybackEngines/WebGLSupport\\BuildTools\\lib\\modules\\WebGLSupport_InputLegacyModule_Dynamic.bc --additional-libraries=C:/Program Files/Unity/Hub/Editor/2019.2.16f1/Editor/Data/PlaybackEngines/WebGLSupport\\BuildTools\\lib\\modules\\WebGLSupport_InputModule_Dynamic.bc --additional-libraries=C:/Program Files/Unity/Hub/Editor/2019.2.16f1/Editor/Data/PlaybackEngines/WebGLSupport\\BuildTools\\lib\\modules\\WebGLSupport_JSONSerializeModule_Dynamic.bc --additional-libraries=C:/Program Files/Unity/Hub/Editor/2019.2.16f1/Editor/Data/PlaybackEngines/WebGLSupport\\BuildTools\\lib\\modules\\WebGLSupport_LocalizationModule_Dynamic.bc --additional-libraries=C:/Program Files/Unity/Hub/Editor/2019.2.16f1/Editor/Data/PlaybackEngines/WebGLSupport\\BuildTools\\lib\\modules\\WebGLSupport_ParticleSystemModule_Dynamic.bc --additional-libraries=C:/Program Files/Unity/Hub/Editor/2019.2.16f1/Editor/Data/PlaybackEngines/WebGLSupport\\BuildTools\\lib\\modules\\WebGLSupport_PerformanceReportingModule_Dynamic.bc --additional-libraries=C:/Program Files/Unity/Hub/Editor/2019.2.16f1/Editor/Data/PlaybackEngines/WebGLSupport\\BuildTools\\lib\\modules\\WebGLSupport_Physics2DModule_Dynamic.bc --additional-libraries=C:/Program Files/Unity/Hub/Editor/2019.2.16f1/Editor/Data/PlaybackEngines/WebGLSupport\\BuildTools\\lib\\modules\\WebGLSupport_PhysicsModule_Dynamic.bc --additional-libraries=C:/Program Files/Unity/Hub/Editor/2019.2.16f1/Editor/Data/PlaybackEngines/WebGLSupport\\BuildTools\\lib\\modules\\WebGLSupport_ProfilerModule_Dynamic.bc --additional-libraries=C:/Program Files/Unity/Hub/Editor/2019.2.16f1/Editor/Data/PlaybackEngines/WebGLSupport\\BuildTools\\lib\\modules\\WebGLSupport_ScreenCaptureModule_Dynamic.bc --additional-libraries=C:/Program Files/Unity/Hub/Editor/2019.2.16f1/Editor/Data/PlaybackEngines/WebGLSupport\\BuildTools\\lib\\modules\\WebGLSupport_SharedInternalsModule_Dynamic.bc --additional-libraries=C:/Program Files/Unity/Hub/Editor/2019.2.16f1/Editor/Data/PlaybackEngines/WebGLSupport\\BuildTools\\lib\\modules\\WebGLSupport_SpriteMaskModule_Dynamic.bc --additional-libraries=C:/Program Files/Unity/Hub/Editor/2019.2.16f1/Editor/Data/PlaybackEngines/WebGLSupport\\BuildTools\\lib\\modules\\WebGLSupport_SpriteShapeModule_Dynamic.bc --additional-libraries=C:/Program Files/Unity/Hub/Editor/2019.2.16f1/Editor/Data/PlaybackEngines/WebGLSupport\\BuildTools\\lib\\modules\\WebGLSupport_StreamingModule_Dynamic.bc --additional-libraries=C:/Program Files/Unity/Hub/Editor/2019.2.16f1/Editor/Data/PlaybackEngines/WebGLSupport\\BuildTools\\lib\\modules\\WebGLSupport_SubstanceModule_Dynamic.bc --additional-libraries=C:/Program Files/Unity/Hub/Editor/2019.2.16f1/Editor/Data/PlaybackEngines/WebGLSupport\\BuildTools\\lib\\modules\\WebGLSupport_TerrainModule_Dynamic.bc --additional-libraries=C:/Program Files/Unity/Hub/Editor/2019.2.16f1/Editor/Data/PlaybackEngines/WebGLSupport\\BuildTools\\lib\\modules\\WebGLSupport_TerrainPhysicsModule_Dynamic.bc --additional-libraries=C:/Program Files/Unity/Hub/Editor/2019.2.16f1/Editor/Data/PlaybackEngines/WebGLSupport\\BuildTools\\lib\\modules\\WebGLSupport_TextCoreModule_Dynamic.bc --additional-libraries=C:/Program Files/Unity/Hub/Editor/2019.2.16f1/Editor/Data/PlaybackEngines/WebGLSupport\\BuildTools\\lib\\modules\\WebGLSupport_TextRenderingModule_Dynamic.bc --additional-libraries=C:/Program Files/Unity/Hub/Editor/2019.2.16f1/Editor/Data/PlaybackEngines/WebGLSupport\\BuildTools\\lib\\modules\\WebGLSupport_TilemapModule_Dynamic.bc --additional-libraries=C:/Program Files/Unity/Hub/Editor/2019.2.16f1/Editor/Data/PlaybackEngines/WebGLSupport\\BuildTools\\lib\\modules\\WebGLSupport_TLSModule_Dynamic.bc --additional-libraries=C:/Program Files/Unity/Hub/Editor/2019.2.16f1/Editor/Data/PlaybackEngines/WebGLSupport\\BuildTools\\lib\\modules\\WebGLSupport_UIElementsModule_Dynamic.bc --additional-libraries=C:/Program Files/Unity/Hub/Editor/2019.2.16f1/Editor/Data/PlaybackEngines/WebGLSupport\\BuildTools\\lib\\modules\\WebGLSupport_UIModule_Dynamic.bc --additional-libraries=C:/Program Files/Unity/Hub/Editor/2019.2.16f1/Editor/Data/PlaybackEngines/WebGLSupport\\BuildTools\\lib\\modules\\WebGLSupport_UmbraModule_Dynamic.bc --additional-libraries=C:/Program Files/Unity/Hub/Editor/2019.2.16f1/Editor/Data/PlaybackEngines/WebGLSupport\\BuildTools\\lib\\modules\\WebGLSupport_UNETModule_Dynamic.bc --additional-libraries=C:/Program Files/Unity/Hub/Editor/2019.2.16f1/Editor/Data/PlaybackEngines/WebGLSupport\\BuildTools\\lib\\modules\\WebGLSupport_UnityAnalyticsModule_Dynamic.bc --additional-libraries=C:/Program Files/Unity/Hub/Editor/2019.2.16f1/Editor/Data/PlaybackEngines/WebGLSupport\\BuildTools\\lib\\modules\\WebGLSupport_UnityConnectModule_Dynamic.bc --additional-libraries=C:/Program Files/Unity/Hub/Editor/2019.2.16f1/Editor/Data/PlaybackEngines/WebGLSupport\\BuildTools\\lib\\modules\\WebGLSupport_UnityTestProtocolModule_Dynamic.bc --additional-libraries=C:/Program Files/Unity/Hub/Editor/2019.2.16f1/Editor/Data/PlaybackEngines/WebGLSupport\\BuildTools\\lib\\modules\\WebGLSupport_UnityWebRequestAssetBundleModule_Dynamic.bc --additional-libraries=C:/Program Files/Unity/Hub/Editor/2019.2.16f1/Editor/Data/PlaybackEngines/WebGLSupport\\BuildTools\\lib\\modules\\WebGLSupport_UnityWebRequestAudioModule_Dynamic.bc --additional-libraries=C:/Program Files/Unity/Hub/Editor/2019.2.16f1/Editor/Data/PlaybackEngines/WebGLSupport\\BuildTools\\lib\\modules\\WebGLSupport_UnityWebRequestModule_Dynamic.bc --additional-libraries=C:/Program Files/Unity/Hub/Editor/2019.2.16f1/Editor/Data/PlaybackEngines/WebGLSupport\\BuildTools\\lib\\modules\\WebGLSupport_UnityWebRequestTextureModule_Dynamic.bc --additional-libraries=C:/Program Files/Unity/Hub/Editor/2019.2.16f1/Editor/Data/PlaybackEngines/WebGLSupport\\BuildTools\\lib\\modules\\WebGLSupport_UnityWebRequestWWWModule_Dynamic.bc --additional-libraries=C:/Program Files/Unity/Hub/Editor/2019.2.16f1/Editor/Data/PlaybackEngines/WebGLSupport\\BuildTools\\lib\\modules\\WebGLSupport_VehiclesModule_Dynamic.bc --additional-libraries=C:/Program Files/Unity/Hub/Editor/2019.2.16f1/Editor/Data/PlaybackEngines/WebGLSupport\\BuildTools\\lib\\modules\\WebGLSupport_VFXModule_Dynamic.bc --additional-libraries=C:/Program Files/Unity/Hub/Editor/2019.2.16f1/Editor/Data/PlaybackEngines/WebGLSupport\\BuildTools\\lib\\modules\\WebGLSupport_VideoModule_Dynamic.bc --additional-libraries=C:/Program Files/Unity/Hub/Editor/2019.2.16f1/Editor/Data/PlaybackEngines/WebGLSupport\\BuildTools\\lib\\modules\\WebGLSupport_VRModule_Dynamic.bc --additional-libraries=C:/Program Files/Unity/Hub/Editor/2019.2.16f1/Editor/Data/PlaybackEngines/WebGLSupport\\BuildTools\\lib\\modules\\WebGLSupport_WebGLModule_Dynamic.bc --additional-libraries=C:/Program Files/Unity/Hub/Editor/2019.2.16f1/Editor/Data/PlaybackEngines/WebGLSupport\\BuildTools\\lib\\modules\\WebGLSupport_WindModule_Dynamic.bc --additional-libraries=C:/Program Files/Unity/Hub/Editor/2019.2.16f1/Editor/Data/PlaybackEngines/WebGLSupport\\BuildTools\\lib\\modules\\WebGLSupport_XRModule_Dynamic.bc --profiler-report --map-file-parser=C:/Program Files/Unity/Hub/Editor/2019.2.16f1/Editor/Data/Tools/MapFileParser/MapFileParser.exe --directory=C:/Users/Marti/Documents/GitHub/RPG-201920/rpg_201920/Temp/StagingArea/Data/Managed --generatedcppdir=C:/Users/Marti/Documents/GitHub/RPG-201920/rpg_201920/Temp/StagingArea/Data/il2cppOutput",
"meta_user_name": "marti_1he0xyh",
"meta_os_version": "Microsoft Windows NT 6.2.9200.0",
"meta_cpu_count": "4"}
